[{"squad":"1st","date":"2021-09-04","team":"EGRFC","lineouts_won":15,"lineouts_total":16,"lineouts_success_rate":0.9375,"scrums_won":8,"scrums_total":8,"scrums_success_rate":1.0,"entries_22m":null,"points":26,"tries":null,"points_per_entry":null,"tries_per_entry":null,"game_id":"2021-09-04_1st_Horsham","season":"2021\/22","opposition":"Horsham II"},{"squad":"1st","date":"2021-09-04","team":"Opposition","lineouts_won":11,"lineouts_total":13,"lineouts_success_rate":0.8461538462,"scrums_won":3,"scrums_total":4,"scrums_success_rate":0.75,"entries_22m":null,"points":56,"tries":null,"points_per_entry":null,"tries_per_entry":null,"game_id":"2021-09-04_1st_Horsham","season":"2021\/22","opposition":"Horsham II"},{"squad":"1st","date":"2021-09-25","team":"EGRFC","lineouts_won":15,"lineouts_total":17,"lineouts_success_rate":0.8823529412,"scrums_won":4,"scrums_total":4,"scrums_success_rate":1.0,"entries_22m":null,"points":47,"tries":null,"points_per_entry":null,"tries_per_entry":null,"game_id":"2021-09-25_1st_Eastbourne","season":"2021\/22","opposition":"Eastbourne"},{"squad":"1st","date":"2021-09-25","team":"Opposition","lineouts_won":10,"lineouts_total":16,"lineouts_success_rate":0.625,"scrums_won":5,"scrums_total":6,"scrums_success_rate":0.8333333333,"entries_22m":null,"points":0,"tries":null,"points_per_entry":null,"tries_per_entry":null,"game_id":"2021-09-25_1st_Eastbourne","season":"2021\/22","opposition":"Eastbourne"},{"squad":"1st","date":"2021-10-16","team":"EGRFC","lineouts_won":5,"lineouts_total":6,"lineouts_success_rate":0.8333333333,"scrums_won":5,"scrums_total":6,"scrums_success_rate":0.8333333333,"entries_22m":null,"points":64,"tries":null,"points_per_entry":null,"tries_per_entry":null,"game_id":"2021-10-16_1st_Burgess_Hill","season":"2021\/22","opposition":"Burgess Hill"},{"squad":"1st","date":"2021-10-16","team":"Opposition","lineouts_won":7,"lineouts_total":9,"lineouts_success_rate":0.7777777778,"scrums_won":4,"scrums_total":4,"scrums_success_rate":1.0,"entries_22m":null,"points":15,"tries":null,"points_per_entry":null,"tries_per_entry":null,"game_id":"2021-10-16_1st_Burgess_Hill","season":"2021\/22","opposition":"Burgess Hill"},{"squad":"1st","date":"2021-11-13","team":"EGRFC","lineouts_won":9,"lineouts_total":11,"lineouts_success_rate":0.8181818182,"scrums_won":5,"scrums_total":7,"scrums_success_rate":0.7142857143,"entries_22m":null,"points":43,"tries":null,"points_per_entry":null,"tries_per_entry":null,"game_id":"2021-11-13_1st_Uckfield","season":"2021\/22","opposition":"Uckfield"},{"squad":"1st","date":"2021-11-13","team":"Opposition","lineouts_won":8,"lineouts_total":13,"lineouts_success_rate":0.6153846154,"scrums_won":9,"scrums_total":9,"scrums_success_rate":1.0,"entries_22m":null,"points":0,"tries":null,"points_per_entry":null,"tries_per_entry":null,"game_id":"2021-11-13_1st_Uckfield","season":"2021\/22","opposition":"Uckfield"},{"squad":"1st","date":"2022-02-12","team":"EGRFC","lineouts_won":11,"lineouts_total":12,"lineouts_success_rate":0.9166666667,"scrums_won":4,"scrums_total":5,"scrums_success_rate":0.8,"entries_22m":null,"points":67,"tries":null,"points_per_entry":null,"tries_per_entry":null,"game_id":"2022-02-12_1st_Seaford","season":"2021\/22","opposition":"Seaford"},{"squad":"1st","date":"2022-02-12","team":"Opposition","lineouts_won":8,"lineouts_total":10,"lineouts_success_rate":0.8,"scrums_won":9,"scrums_total":9,"scrums_success_rate":1.0,"entries_22m":null,"points":5,"tries":null,"points_per_entry":null,"tries_per_entry":null,"game_id":"2022-02-12_1st_Seaford","season":"2021\/22","opposition":"Seaford"},{"squad":"1st","date":"2022-02-26","team":"EGRFC","lineouts_won":13,"lineouts_total":14,"lineouts_success_rate":0.9285714286,"scrums_won":5,"scrums_total":5,"scrums_success_rate":1.0,"entries_22m":null,"points":64,"tries":null,"points_per_entry":null,"tries_per_entry":null,"game_id":"2022-02-26_1st_Burgess_Hill","season":"2021\/22","opposition":"Burgess Hill"},{"squad":"1st","date":"2022-02-26","team":"Opposition","lineouts_won":5,"lineouts_total":9,"lineouts_success_rate":0.5555555556,"scrums_won":6,"scrums_total":8,"scrums_success_rate":0.75,"entries_22m":null,"points":30,"tries":null,"points_per_entry":null,"tries_per_entry":null,"game_id":"2022-02-26_1st_Burgess_Hill","season":"2021\/22","opposition":"Burgess Hill"},{"squad":"1st","date":"2022-03-26","team":"EGRFC","lineouts_won":11,"lineouts_total":11,"lineouts_success_rate":1.0,"scrums_won":6,"scrums_total":7,"scrums_success_rate":0.8571428571,"entries_22m":null,"points":35,"tries":null,"points_per_entry":null,"tries_per_entry":null,"game_id":"2022-03-26_1st_Eastbourne","season":"2021\/22","opposition":"Eastbourne"},{"squad":"1st","date":"2022-03-26","team":"Opposition","lineouts_won":5,"lineouts_total":8,"lineouts_success_rate":0.625,"scrums_won":11,"scrums_total":11,"scrums_success_rate":1.0,"entries_22m":null,"points":31,"tries":null,"points_per_entry":null,"tries_per_entry":null,"game_id":"2022-03-26_1st_Eastbourne","season":"2021\/22","opposition":"Eastbourne"},{"squad":"1st","date":"2022-04-02","team":"EGRFC","lineouts_won":5,"lineouts_total":6,"lineouts_success_rate":0.8333333333,"scrums_won":14,"scrums_total":14,"scrums_success_rate":1.0,"entries_22m":null,"points":57,"tries":null,"points_per_entry":null,"tries_per_entry":null,"game_id":"2022-04-02_1st_Uckfield","season":"2021\/22","opposition":"Uckfield"},{"squad":"1st","date":"2022-04-02","team":"Opposition","lineouts_won":6,"lineouts_total":13,"lineouts_success_rate":0.4615384615,"scrums_won":8,"scrums_total":10,"scrums_success_rate":0.8,"entries_22m":null,"points":7,"tries":null,"points_per_entry":null,"tries_per_entry":null,"game_id":"2022-04-02_1st_Uckfield","season":"2021\/22","opposition":"Uckfield"},{"squad":"1st","date":"2022-09-17","team":"EGRFC","lineouts_won":10,"lineouts_total":13,"lineouts_success_rate":0.7692307692,"scrums_won":6,"scrums_total":6,"scrums_success_rate":1.0,"entries_22m":null,"points":69,"tries":null,"points_per_entry":null,"tries_per_entry":null,"game_id":"2022-09-17_1st_Lewes","season":"2022\/23","opposition":"Lewes"},{"squad":"1st","date":"2022-09-17","team":"Opposition","lineouts_won":8,"lineouts_total":10,"lineouts_success_rate":0.8,"scrums_won":7,"scrums_total":10,"scrums_success_rate":0.7,"entries_22m":null,"points":7,"tries":null,"points_per_entry":null,"tries_per_entry":null,"game_id":"2022-09-17_1st_Lewes","season":"2022\/23","opposition":"Lewes"},{"squad":"1st","date":"2022-09-24","team":"EGRFC","lineouts_won":3,"lineouts_total":3,"lineouts_success_rate":1.0,"scrums_won":12,"scrums_total":12,"scrums_success_rate":1.0,"entries_22m":null,"points":58,"tries":null,"points_per_entry":null,"tries_per_entry":null,"game_id":"2022-09-24_1st_Uckfield","season":"2022\/23","opposition":"Uckfield"},{"squad":"1st","date":"2022-09-24","team":"Opposition","lineouts_won":7,"lineouts_total":14,"lineouts_success_rate":0.5,"scrums_won":8,"scrums_total":9,"scrums_success_rate":0.8888888889,"entries_22m":null,"points":3,"tries":null,"points_per_entry":null,"tries_per_entry":null,"game_id":"2022-09-24_1st_Uckfield","season":"2022\/23","opposition":"Uckfield"},{"squad":"1st","date":"2022-10-01","team":"EGRFC","lineouts_won":11,"lineouts_total":11,"lineouts_success_rate":1.0,"scrums_won":6,"scrums_total":9,"scrums_success_rate":0.6666666667,"entries_22m":null,"points":39,"tries":null,"points_per_entry":null,"tries_per_entry":null,"game_id":"2022-10-01_1st_Crawley","season":"2022\/23","opposition":"Crawley"},{"squad":"1st","date":"2022-10-01","team":"Opposition","lineouts_won":6,"lineouts_total":8,"lineouts_success_rate":0.75,"scrums_won":3,"scrums_total":4,"scrums_success_rate":0.75,"entries_22m":null,"points":36,"tries":null,"points_per_entry":null,"tries_per_entry":null,"game_id":"2022-10-01_1st_Crawley","season":"2022\/23","opposition":"Crawley"},{"squad":"1st","date":"2022-10-15","team":"EGRFC","lineouts_won":10,"lineouts_total":10,"lineouts_success_rate":1.0,"scrums_won":10,"scrums_total":10,"scrums_success_rate":1.0,"entries_22m":null,"points":70,"tries":null,"points_per_entry":null,"tries_per_entry":null,"game_id":"2022-10-15_1st_Shoreham","season":"2022\/23","opposition":"Shoreham"},{"squad":"1st","date":"2022-10-15","team":"Opposition","lineouts_won":6,"lineouts_total":9,"lineouts_success_rate":0.6666666667,"scrums_won":6,"scrums_total":6,"scrums_success_rate":1.0,"entries_22m":null,"points":11,"tries":null,"points_per_entry":null,"tries_per_entry":null,"game_id":"2022-10-15_1st_Shoreham","season":"2022\/23","opposition":"Shoreham"},{"squad":"1st","date":"2022-10-22","team":"EGRFC","lineouts_won":6,"lineouts_total":7,"lineouts_success_rate":0.8571428571,"scrums_won":9,"scrums_total":10,"scrums_success_rate":0.9,"entries_22m":null,"points":62,"tries":null,"points_per_entry":null,"tries_per_entry":null,"game_id":"2022-10-22_1st_Seaford","season":"2022\/23","opposition":"Seaford"},{"squad":"1st","date":"2022-10-22","team":"Opposition","lineouts_won":6,"lineouts_total":8,"lineouts_success_rate":0.75,"scrums_won":8,"scrums_total":9,"scrums_success_rate":0.8888888889,"entries_22m":null,"points":17,"tries":null,"points_per_entry":null,"tries_per_entry":null,"game_id":"2022-10-22_1st_Seaford","season":"2022\/23","opposition":"Seaford"},{"squad":"1st","date":"2022-10-29","team":"EGRFC","lineouts_won":13,"lineouts_total":14,"lineouts_success_rate":0.9285714286,"scrums_won":12,"scrums_total":12,"scrums_success_rate":1.0,"entries_22m":null,"points":53,"tries":null,"points_per_entry":null,"tries_per_entry":null,"game_id":"2022-10-29_1st_Burgess_Hill","season":"2022\/23","opposition":"Burgess Hill"},{"squad":"1st","date":"2022-10-29","team":"Opposition","lineouts_won":4,"lineouts_total":6,"lineouts_success_rate":0.6666666667,"scrums_won":13,"scrums_total":14,"scrums_success_rate":0.9285714286,"entries_22m":null,"points":5,"tries":null,"points_per_entry":null,"tries_per_entry":null,"game_id":"2022-10-29_1st_Burgess_Hill","season":"2022\/23","opposition":"Burgess Hill"},{"squad":"1st","date":"2022-11-05","team":"EGRFC","lineouts_won":10,"lineouts_total":14,"lineouts_success_rate":0.7142857143,"scrums_won":4,"scrums_total":5,"scrums_success_rate":0.8,"entries_22m":null,"points":15,"tries":null,"points_per_entry":null,"tries_per_entry":null,"game_id":"2022-11-05_1st_Eastbourne","season":"2022\/23","opposition":"Eastbourne"},{"squad":"1st","date":"2022-11-05","team":"Opposition","lineouts_won":13,"lineouts_total":14,"lineouts_success_rate":0.9285714286,"scrums_won":10,"scrums_total":10,"scrums_success_rate":1.0,"entries_22m":null,"points":29,"tries":null,"points_per_entry":null,"tries_per_entry":null,"game_id":"2022-11-05_1st_Eastbourne","season":"2022\/23","opposition":"Eastbourne"},{"squad":"1st","date":"2022-11-26","team":"EGRFC","lineouts_won":9,"lineouts_total":13,"lineouts_success_rate":0.6923076923,"scrums_won":11,"scrums_total":11,"scrums_success_rate":1.0,"entries_22m":null,"points":35,"tries":null,"points_per_entry":null,"tries_per_entry":null,"game_id":"2022-11-26_1st_Haywards_Heath","season":"2022\/23","opposition":"Haywards Heath"},{"squad":"1st","date":"2022-11-26","team":"Opposition","lineouts_won":7,"lineouts_total":11,"lineouts_success_rate":0.6363636364,"scrums_won":10,"scrums_total":11,"scrums_success_rate":0.9090909091,"entries_22m":null,"points":17,"tries":null,"points_per_entry":null,"tries_per_entry":null,"game_id":"2022-11-26_1st_Haywards_Heath","season":"2022\/23","opposition":"Haywards Heath"},{"squad":"1st","date":"2022-12-10","team":"EGRFC","lineouts_won":4,"lineouts_total":5,"lineouts_success_rate":0.8,"scrums_won":6,"scrums_total":6,"scrums_success_rate":1.0,"entries_22m":null,"points":75,"tries":null,"points_per_entry":null,"tries_per_entry":null,"game_id":"2022-12-10_1st_Crawley","season":"2022\/23","opposition":"Crawley"},{"squad":"1st","date":"2022-12-10","team":"Opposition","lineouts_won":8,"lineouts_total":9,"lineouts_success_rate":0.8888888889,"scrums_won":4,"scrums_total":6,"scrums_success_rate":0.6666666667,"entries_22m":null,"points":12,"tries":null,"points_per_entry":null,"tries_per_entry":null,"game_id":"2022-12-10_1st_Crawley","season":"2022\/23","opposition":"Crawley"},{"squad":"1st","date":"2023-01-14","team":"EGRFC","lineouts_won":8,"lineouts_total":9,"lineouts_success_rate":0.8888888889,"scrums_won":6,"scrums_total":6,"scrums_success_rate":1.0,"entries_22m":null,"points":57,"tries":null,"points_per_entry":null,"tries_per_entry":null,"game_id":"2023-01-14_1st_Shoreham","season":"2022\/23","opposition":"Shoreham"},{"squad":"1st","date":"2023-01-14","team":"Opposition","lineouts_won":8,"lineouts_total":15,"lineouts_success_rate":0.5333333333,"scrums_won":5,"scrums_total":6,"scrums_success_rate":0.8333333333,"entries_22m":null,"points":14,"tries":null,"points_per_entry":null,"tries_per_entry":null,"game_id":"2023-01-14_1st_Shoreham","season":"2022\/23","opposition":"Shoreham"},{"squad":"1st","date":"2023-01-21","team":"EGRFC","lineouts_won":11,"lineouts_total":13,"lineouts_success_rate":0.8461538462,"scrums_won":8,"scrums_total":9,"scrums_success_rate":0.8888888889,"entries_22m":null,"points":43,"tries":null,"points_per_entry":null,"tries_per_entry":null,"game_id":"2023-01-21_1st_Seaford","season":"2022\/23","opposition":"Seaford"},{"squad":"1st","date":"2023-01-21","team":"Opposition","lineouts_won":6,"lineouts_total":10,"lineouts_success_rate":0.6,"scrums_won":6,"scrums_total":8,"scrums_success_rate":0.75,"entries_22m":null,"points":5,"tries":null,"points_per_entry":null,"tries_per_entry":null,"game_id":"2023-01-21_1st_Seaford","season":"2022\/23","opposition":"Seaford"},{"squad":"1st","date":"2023-01-28","team":"EGRFC","lineouts_won":12,"lineouts_total":14,"lineouts_success_rate":0.8571428571,"scrums_won":7,"scrums_total":7,"scrums_success_rate":1.0,"entries_22m":null,"points":63,"tries":null,"points_per_entry":null,"tries_per_entry":null,"game_id":"2023-01-28_1st_Burgess_Hill","season":"2022\/23","opposition":"Burgess Hill"},{"squad":"1st","date":"2023-01-28","team":"Opposition","lineouts_won":5,"lineouts_total":7,"lineouts_success_rate":0.7142857143,"scrums_won":12,"scrums_total":12,"scrums_success_rate":1.0,"entries_22m":null,"points":0,"tries":null,"points_per_entry":null,"tries_per_entry":null,"game_id":"2023-01-28_1st_Burgess_Hill","season":"2022\/23","opposition":"Burgess Hill"},{"squad":"1st","date":"2023-02-11","team":"EGRFC","lineouts_won":9,"lineouts_total":9,"lineouts_success_rate":1.0,"scrums_won":8,"scrums_total":10,"scrums_success_rate":0.8,"entries_22m":null,"points":38,"tries":null,"points_per_entry":null,"tries_per_entry":null,"game_id":"2023-02-11_1st_Eastbourne","season":"2022\/23","opposition":"Eastbourne"},{"squad":"1st","date":"2023-02-11","team":"Opposition","lineouts_won":11,"lineouts_total":12,"lineouts_success_rate":0.9166666667,"scrums_won":2,"scrums_total":2,"scrums_success_rate":1.0,"entries_22m":null,"points":32,"tries":null,"points_per_entry":null,"tries_per_entry":null,"game_id":"2023-02-11_1st_Eastbourne","season":"2022\/23","opposition":"Eastbourne"},{"squad":"1st","date":"2023-02-18","team":"EGRFC","lineouts_won":11,"lineouts_total":11,"lineouts_success_rate":1.0,"scrums_won":6,"scrums_total":6,"scrums_success_rate":1.0,"entries_22m":null,"points":35,"tries":null,"points_per_entry":null,"tries_per_entry":null,"game_id":"2023-02-18_1st_Pulborough","season":"2022\/23","opposition":"Pulborough"},{"squad":"1st","date":"2023-02-18","team":"Opposition","lineouts_won":8,"lineouts_total":13,"lineouts_success_rate":0.6153846154,"scrums_won":7,"scrums_total":8,"scrums_success_rate":0.875,"entries_22m":null,"points":14,"tries":null,"points_per_entry":null,"tries_per_entry":null,"game_id":"2023-02-18_1st_Pulborough","season":"2022\/23","opposition":"Pulborough"},{"squad":"1st","date":"2023-03-04","team":"EGRFC","lineouts_won":8,"lineouts_total":12,"lineouts_success_rate":0.6666666667,"scrums_won":12,"scrums_total":12,"scrums_success_rate":1.0,"entries_22m":null,"points":54,"tries":null,"points_per_entry":null,"tries_per_entry":null,"game_id":"2023-03-04_1st_Haywards_Heath","season":"2022\/23","opposition":"Haywards Heath"},{"squad":"1st","date":"2023-03-04","team":"Opposition","lineouts_won":12,"lineouts_total":14,"lineouts_success_rate":0.8571428571,"scrums_won":6,"scrums_total":6,"scrums_success_rate":1.0,"entries_22m":null,"points":17,"tries":null,"points_per_entry":null,"tries_per_entry":null,"game_id":"2023-03-04_1st_Haywards_Heath","season":"2022\/23","opposition":"Haywards Heath"},{"squad":"1st","date":"2023-04-22","team":"EGRFC","lineouts_won":5,"lineouts_total":6,"lineouts_success_rate":0.8333333333,"scrums_won":7,"scrums_total":7,"scrums_success_rate":1.0,"entries_22m":null,"points":29,"tries":null,"points_per_entry":null,"tries_per_entry":null,"game_id":"2023-04-22_1st_Cheshunt","season":"2022\/23","opposition":"Cheshunt"},{"squad":"1st","date":"2023-04-22","team":"Opposition","lineouts_won":11,"lineouts_total":14,"lineouts_success_rate":0.7857142857,"scrums_won":2,"scrums_total":2,"scrums_success_rate":1.0,"entries_22m":null,"points":25,"tries":null,"points_per_entry":null,"tries_per_entry":null,"game_id":"2023-04-22_1st_Cheshunt","season":"2022\/23","opposition":"Cheshunt"},{"squad":"1st","date":"2023-04-29","team":"EGRFC","lineouts_won":10,"lineouts_total":13,"lineouts_success_rate":0.7692307692,"scrums_won":5,"scrums_total":5,"scrums_success_rate":1.0,"entries_22m":null,"points":21,"tries":null,"points_per_entry":null,"tries_per_entry":null,"game_id":"2023-04-29_1st_Wensleydale","season":"2022\/23","opposition":"Wensleydale"},{"squad":"1st","date":"2023-04-29","team":"Opposition","lineouts_won":11,"lineouts_total":12,"lineouts_success_rate":0.9166666667,"scrums_won":5,"scrums_total":7,"scrums_success_rate":0.7142857143,"entries_22m":null,"points":35,"tries":null,"points_per_entry":null,"tries_per_entry":null,"game_id":"2023-04-29_1st_Wensleydale","season":"2022\/23","opposition":"Wensleydale"},{"squad":"1st","date":"2023-08-19","team":"EGRFC","lineouts_won":3,"lineouts_total":7,"lineouts_success_rate":0.4285714286,"scrums_won":10,"scrums_total":10,"scrums_success_rate":1.0,"entries_22m":null,"points":19,"tries":null,"points_per_entry":null,"tries_per_entry":null,"game_id":"2023-08-19_1st_Old_Colfeians","season":"2023\/24","opposition":"Old Colfeians"},{"squad":"1st","date":"2023-08-19","team":"Opposition","lineouts_won":4,"lineouts_total":8,"lineouts_success_rate":0.5,"scrums_won":6,"scrums_total":7,"scrums_success_rate":0.8571428571,"entries_22m":null,"points":36,"tries":null,"points_per_entry":null,"tries_per_entry":null,"game_id":"2023-08-19_1st_Old_Colfeians","season":"2023\/24","opposition":"Old Colfeians"},{"squad":"1st","date":"2023-09-02","team":"EGRFC","lineouts_won":11,"lineouts_total":20,"lineouts_success_rate":0.55,"scrums_won":7,"scrums_total":8,"scrums_success_rate":0.875,"entries_22m":null,"points":0,"tries":null,"points_per_entry":null,"tries_per_entry":null,"game_id":"2023-09-02_1st_Heathfield_&_Waldron","season":"2023\/24","opposition":"Heathfield & Waldron"},{"squad":"1st","date":"2023-09-02","team":"Opposition","lineouts_won":10,"lineouts_total":13,"lineouts_success_rate":0.7692307692,"scrums_won":7,"scrums_total":9,"scrums_success_rate":0.7777777778,"entries_22m":null,"points":5,"tries":null,"points_per_entry":null,"tries_per_entry":null,"game_id":"2023-09-02_1st_Heathfield_&_Waldron","season":"2023\/24","opposition":"Heathfield & Waldron"},{"squad":"1st","date":"2023-09-16","team":"EGRFC","lineouts_won":4,"lineouts_total":12,"lineouts_success_rate":0.3333333333,"scrums_won":8,"scrums_total":10,"scrums_success_rate":0.8,"entries_22m":null,"points":8,"tries":null,"points_per_entry":null,"tries_per_entry":null,"game_id":"2023-09-16_1st_Twickenham","season":"2023\/24","opposition":"Twickenham"},{"squad":"1st","date":"2023-09-16","team":"Opposition","lineouts_won":9,"lineouts_total":15,"lineouts_success_rate":0.6,"scrums_won":5,"scrums_total":5,"scrums_success_rate":1.0,"entries_22m":null,"points":48,"tries":null,"points_per_entry":null,"tries_per_entry":null,"game_id":"2023-09-16_1st_Twickenham","season":"2023\/24","opposition":"Twickenham"},{"squad":"1st","date":"2023-09-23","team":"EGRFC","lineouts_won":9,"lineouts_total":10,"lineouts_success_rate":0.9,"scrums_won":8,"scrums_total":8,"scrums_success_rate":1.0,"entries_22m":null,"points":27,"tries":null,"points_per_entry":null,"tries_per_entry":null,"game_id":"2023-09-23_1st_Trinity","season":"2023\/24","opposition":"Trinity"},{"squad":"1st","date":"2023-09-23","team":"Opposition","lineouts_won":12,"lineouts_total":14,"lineouts_success_rate":0.8571428571,"scrums_won":8,"scrums_total":9,"scrums_success_rate":0.8888888889,"entries_22m":null,"points":22,"tries":null,"points_per_entry":null,"tries_per_entry":null,"game_id":"2023-09-23_1st_Trinity","season":"2023\/24","opposition":"Trinity"},{"squad":"1st","date":"2023-09-30","team":"EGRFC","lineouts_won":11,"lineouts_total":14,"lineouts_success_rate":0.7857142857,"scrums_won":9,"scrums_total":10,"scrums_success_rate":0.9,"entries_22m":null,"points":22,"tries":null,"points_per_entry":null,"tries_per_entry":null,"game_id":"2023-09-30_1st_KCS_Old_Boys","season":"2023\/24","opposition":"KCS Old Boys"},{"squad":"1st","date":"2023-09-30","team":"Opposition","lineouts_won":7,"lineouts_total":7,"lineouts_success_rate":1.0,"scrums_won":7,"scrums_total":9,"scrums_success_rate":0.7777777778,"entries_22m":null,"points":26,"tries":null,"points_per_entry":null,"tries_per_entry":null,"game_id":"2023-09-30_1st_KCS_Old_Boys","season":"2023\/24","opposition":"KCS Old Boys"},{"squad":"1st","date":"2023-10-14","team":"EGRFC","lineouts_won":8,"lineouts_total":12,"lineouts_success_rate":0.6666666667,"scrums_won":10,"scrums_total":12,"scrums_success_rate":0.8333333333,"entries_22m":null,"points":20,"tries":null,"points_per_entry":null,"tries_per_entry":null,"game_id":"2023-10-14_1st_Kingston","season":"2023\/24","opposition":"Kingston"},{"squad":"1st","date":"2023-10-14","team":"Opposition","lineouts_won":8,"lineouts_total":11,"lineouts_success_rate":0.7272727273,"scrums_won":6,"scrums_total":7,"scrums_success_rate":0.8571428571,"entries_22m":null,"points":11,"tries":null,"points_per_entry":null,"tries_per_entry":null,"game_id":"2023-10-14_1st_Kingston","season":"2023\/24","opposition":"Kingston"},{"squad":"1st","date":"2023-10-21","team":"EGRFC","lineouts_won":11,"lineouts_total":15,"lineouts_success_rate":0.7333333333,"scrums_won":8,"scrums_total":8,"scrums_success_rate":1.0,"entries_22m":null,"points":25,"tries":null,"points_per_entry":null,"tries_per_entry":null,"game_id":"2023-10-21_1st_Old_Walcountians","season":"2023\/24","opposition":"Old Walcountians"},{"squad":"1st","date":"2023-10-21","team":"Opposition","lineouts_won":10,"lineouts_total":11,"lineouts_success_rate":0.9090909091,"scrums_won":4,"scrums_total":7,"scrums_success_rate":0.5714285714,"entries_22m":null,"points":34,"tries":null,"points_per_entry":null,"tries_per_entry":null,"game_id":"2023-10-21_1st_Old_Walcountians","season":"2023\/24","opposition":"Old Walcountians"},{"squad":"1st","date":"2023-11-11","team":"EGRFC","lineouts_won":14,"lineouts_total":21,"lineouts_success_rate":0.6666666667,"scrums_won":13,"scrums_total":13,"scrums_success_rate":1.0,"entries_22m":null,"points":10,"tries":null,"points_per_entry":null,"tries_per_entry":null,"game_id":"2023-11-11_1st_Teddington","season":"2023\/24","opposition":"Teddington"},{"squad":"1st","date":"2023-11-11","team":"Opposition","lineouts_won":11,"lineouts_total":12,"lineouts_success_rate":0.9166666667,"scrums_won":7,"scrums_total":8,"scrums_success_rate":0.875,"entries_22m":null,"points":27,"tries":null,"points_per_entry":null,"tries_per_entry":null,"game_id":"2023-11-11_1st_Teddington","season":"2023\/24","opposition":"Teddington"},{"squad":"1st","date":"2023-11-18","team":"EGRFC","lineouts_won":7,"lineouts_total":11,"lineouts_success_rate":0.6363636364,"scrums_won":9,"scrums_total":10,"scrums_success_rate":0.9,"entries_22m":null,"points":24,"tries":null,"points_per_entry":null,"tries_per_entry":null,"game_id":"2023-11-18_1st_Eastbourne","season":"2023\/24","opposition":"Eastbourne"},{"squad":"1st","date":"2023-11-18","team":"Opposition","lineouts_won":8,"lineouts_total":14,"lineouts_success_rate":0.5714285714,"scrums_won":7,"scrums_total":8,"scrums_success_rate":0.875,"entries_22m":null,"points":26,"tries":null,"points_per_entry":null,"tries_per_entry":null,"game_id":"2023-11-18_1st_Eastbourne","season":"2023\/24","opposition":"Eastbourne"},{"squad":"1st","date":"2023-11-25","team":"EGRFC","lineouts_won":10,"lineouts_total":12,"lineouts_success_rate":0.8333333333,"scrums_won":8,"scrums_total":8,"scrums_success_rate":1.0,"entries_22m":null,"points":20,"tries":null,"points_per_entry":null,"tries_per_entry":null,"game_id":"2023-11-25_1st_Horsham","season":"2023\/24","opposition":"Horsham II"},{"squad":"1st","date":"2023-11-25","team":"Opposition","lineouts_won":16,"lineouts_total":16,"lineouts_success_rate":1.0,"scrums_won":1,"scrums_total":6,"scrums_success_rate":0.1666666667,"entries_22m":null,"points":31,"tries":null,"points_per_entry":null,"tries_per_entry":null,"game_id":"2023-11-25_1st_Horsham","season":"2023\/24","opposition":"Horsham II"},{"squad":"1st","date":"2023-12-02","team":"EGRFC","lineouts_won":14,"lineouts_total":17,"lineouts_success_rate":0.8235294118,"scrums_won":7,"scrums_total":8,"scrums_success_rate":0.875,"entries_22m":null,"points":24,"tries":null,"points_per_entry":null,"tries_per_entry":null,"game_id":"2023-12-02_1st_Weybridge_Vandals","season":"2023\/24","opposition":"Weybridge Vandals"},{"squad":"1st","date":"2023-12-02","team":"Opposition","lineouts_won":12,"lineouts_total":12,"lineouts_success_rate":1.0,"scrums_won":3,"scrums_total":6,"scrums_success_rate":0.5,"entries_22m":null,"points":28,"tries":null,"points_per_entry":null,"tries_per_entry":null,"game_id":"2023-12-02_1st_Weybridge_Vandals","season":"2023\/24","opposition":"Weybridge Vandals"},{"squad":"1st","date":"2023-12-09","team":"EGRFC","lineouts_won":9,"lineouts_total":13,"lineouts_success_rate":0.6923076923,"scrums_won":10,"scrums_total":11,"scrums_success_rate":0.9090909091,"entries_22m":null,"points":26,"tries":null,"points_per_entry":null,"tries_per_entry":null,"game_id":"2023-12-09_1st_Hove","season":"2023\/24","opposition":"Hove"},{"squad":"1st","date":"2023-12-09","team":"Opposition","lineouts_won":7,"lineouts_total":9,"lineouts_success_rate":0.7777777778,"scrums_won":5,"scrums_total":7,"scrums_success_rate":0.7142857143,"entries_22m":null,"points":12,"tries":null,"points_per_entry":null,"tries_per_entry":null,"game_id":"2023-12-09_1st_Hove","season":"2023\/24","opposition":"Hove"},{"squad":"1st","date":"2023-12-16","team":"EGRFC","lineouts_won":12,"lineouts_total":15,"lineouts_success_rate":0.8,"scrums_won":8,"scrums_total":10,"scrums_success_rate":0.8,"entries_22m":null,"points":41,"tries":null,"points_per_entry":null,"tries_per_entry":null,"game_id":"2023-12-16_1st_Trinity","season":"2023\/24","opposition":"Trinity"},{"squad":"1st","date":"2023-12-16","team":"Opposition","lineouts_won":6,"lineouts_total":11,"lineouts_success_rate":0.5454545455,"scrums_won":0,"scrums_total":11,"scrums_success_rate":0.0,"entries_22m":null,"points":10,"tries":null,"points_per_entry":null,"tries_per_entry":null,"game_id":"2023-12-16_1st_Trinity","season":"2023\/24","opposition":"Trinity"},{"squad":"1st","date":"2024-01-13","team":"EGRFC","lineouts_won":12,"lineouts_total":14,"lineouts_success_rate":0.8571428571,"scrums_won":3,"scrums_total":4,"scrums_success_rate":0.75,"entries_22m":null,"points":18,"tries":null,"points_per_entry":null,"tries_per_entry":null,"game_id":"2024-01-13_1st_Old_Tiffinians","season":"2023\/24","opposition":"Old Tiffinians"},{"squad":"1st","date":"2024-01-13","team":"Opposition","lineouts_won":10,"lineouts_total":11,"lineouts_success_rate":0.9090909091,"scrums_won":4,"scrums_total":4,"scrums_success_rate":1.0,"entries_22m":null,"points":39,"tries":null,"points_per_entry":null,"tries_per_entry":null,"game_id":"2024-01-13_1st_Old_Tiffinians","season":"2023\/24","opposition":"Old Tiffinians"},{"squad":"1st","date":"2024-01-27","team":"EGRFC","lineouts_won":10,"lineouts_total":11,"lineouts_success_rate":0.9090909091,"scrums_won":4,"scrums_total":4,"scrums_success_rate":1.0,"entries_22m":null,"points":38,"tries":null,"points_per_entry":null,"tries_per_entry":null,"game_id":"2024-01-27_1st_Old_Walcountians","season":"2023\/24","opposition":"Old Walcountians"},{"squad":"1st","date":"2024-01-27","team":"Opposition","lineouts_won":11,"lineouts_total":12,"lineouts_success_rate":0.9166666667,"scrums_won":6,"scrums_total":11,"scrums_success_rate":0.5454545455,"entries_22m":null,"points":19,"tries":null,"points_per_entry":null,"tries_per_entry":null,"game_id":"2024-01-27_1st_Old_Walcountians","season":"2023\/24","opposition":"Old Walcountians"},{"squad":"1st","date":"2024-02-17","team":"EGRFC","lineouts_won":13,"lineouts_total":21,"lineouts_success_rate":0.619047619,"scrums_won":10,"scrums_total":12,"scrums_success_rate":0.8333333333,"entries_22m":null,"points":0,"tries":null,"points_per_entry":null,"tries_per_entry":null,"game_id":"2024-02-17_1st_Teddington","season":"2023\/24","opposition":"Teddington"},{"squad":"1st","date":"2024-02-17","team":"Opposition","lineouts_won":8,"lineouts_total":13,"lineouts_success_rate":0.6153846154,"scrums_won":14,"scrums_total":14,"scrums_success_rate":1.0,"entries_22m":null,"points":26,"tries":null,"points_per_entry":null,"tries_per_entry":null,"game_id":"2024-02-17_1st_Teddington","season":"2023\/24","opposition":"Teddington"},{"squad":"1st","date":"2024-03-02","team":"EGRFC","lineouts_won":8,"lineouts_total":11,"lineouts_success_rate":0.7272727273,"scrums_won":8,"scrums_total":8,"scrums_success_rate":1.0,"entries_22m":null,"points":15,"tries":null,"points_per_entry":null,"tries_per_entry":null,"game_id":"2024-03-02_1st_Eastbourne","season":"2023\/24","opposition":"Eastbourne"},{"squad":"1st","date":"2024-03-02","team":"Opposition","lineouts_won":10,"lineouts_total":11,"lineouts_success_rate":0.9090909091,"scrums_won":13,"scrums_total":13,"scrums_success_rate":1.0,"entries_22m":null,"points":14,"tries":null,"points_per_entry":null,"tries_per_entry":null,"game_id":"2024-03-02_1st_Eastbourne","season":"2023\/24","opposition":"Eastbourne"},{"squad":"1st","date":"2024-03-16","team":"EGRFC","lineouts_won":7,"lineouts_total":13,"lineouts_success_rate":0.5384615385,"scrums_won":4,"scrums_total":5,"scrums_success_rate":0.8,"entries_22m":null,"points":26,"tries":null,"points_per_entry":null,"tries_per_entry":null,"game_id":"2024-03-16_1st_Weybridge_Vandals","season":"2023\/24","opposition":"Weybridge Vandals"},{"squad":"1st","date":"2024-03-16","team":"Opposition","lineouts_won":6,"lineouts_total":10,"lineouts_success_rate":0.6,"scrums_won":4,"scrums_total":4,"scrums_success_rate":1.0,"entries_22m":null,"points":66,"tries":null,"points_per_entry":null,"tries_per_entry":null,"game_id":"2024-03-16_1st_Weybridge_Vandals","season":"2023\/24","opposition":"Weybridge Vandals"},{"squad":"1st","date":"2024-03-23","team":"EGRFC","lineouts_won":13,"lineouts_total":14,"lineouts_success_rate":0.9285714286,"scrums_won":6,"scrums_total":6,"scrums_success_rate":1.0,"entries_22m":null,"points":13,"tries":null,"points_per_entry":null,"tries_per_entry":null,"game_id":"2024-03-23_1st_Hove","season":"2023\/24","opposition":"Hove"},{"squad":"1st","date":"2024-03-23","team":"Opposition","lineouts_won":14,"lineouts_total":15,"lineouts_success_rate":0.9333333333,"scrums_won":10,"scrums_total":10,"scrums_success_rate":1.0,"entries_22m":null,"points":15,"tries":null,"points_per_entry":null,"tries_per_entry":null,"game_id":"2024-03-23_1st_Hove","season":"2023\/24","opposition":"Hove"},{"squad":"1st","date":"2024-04-06","team":"EGRFC","lineouts_won":11,"lineouts_total":19,"lineouts_success_rate":0.5789473684,"scrums_won":6,"scrums_total":6,"scrums_success_rate":1.0,"entries_22m":null,"points":10,"tries":null,"points_per_entry":null,"tries_per_entry":null,"game_id":"2024-04-06_1st_Twickenham","season":"2023\/24","opposition":"Twickenham"},{"squad":"1st","date":"2024-04-06","team":"Opposition","lineouts_won":7,"lineouts_total":7,"lineouts_success_rate":1.0,"scrums_won":5,"scrums_total":5,"scrums_success_rate":1.0,"entries_22m":null,"points":35,"tries":null,"points_per_entry":null,"tries_per_entry":null,"game_id":"2024-04-06_1st_Twickenham","season":"2023\/24","opposition":"Twickenham"},{"squad":"1st","date":"2024-04-13","team":"EGRFC","lineouts_won":6,"lineouts_total":9,"lineouts_success_rate":0.6666666667,"scrums_won":15,"scrums_total":15,"scrums_success_rate":1.0,"entries_22m":null,"points":42,"tries":null,"points_per_entry":null,"tries_per_entry":null,"game_id":"2024-04-13_1st_Dover","season":"2023\/24","opposition":"Dover"},{"squad":"1st","date":"2024-04-13","team":"Opposition","lineouts_won":5,"lineouts_total":7,"lineouts_success_rate":0.7142857143,"scrums_won":3,"scrums_total":3,"scrums_success_rate":1.0,"entries_22m":null,"points":36,"tries":null,"points_per_entry":null,"tries_per_entry":null,"game_id":"2024-04-13_1st_Dover","season":"2023\/24","opposition":"Dover"},{"squad":"1st","date":"2024-09-07","team":"EGRFC","lineouts_won":11,"lineouts_total":13,"lineouts_success_rate":0.8461538462,"scrums_won":7,"scrums_total":7,"scrums_success_rate":1.0,"entries_22m":7,"points":16,"tries":2,"points_per_entry":2.3,"tries_per_entry":0.2857142857,"game_id":"2024-09-07_1st_London_Cornish","season":"2024\/25","opposition":"London Cornish"},{"squad":"1st","date":"2024-09-07","team":"Opposition","lineouts_won":9,"lineouts_total":10,"lineouts_success_rate":0.9,"scrums_won":5,"scrums_total":7,"scrums_success_rate":0.7142857143,"entries_22m":6,"points":18,"tries":2,"points_per_entry":3.0,"tries_per_entry":0.3333333333,"game_id":"2024-09-07_1st_London_Cornish","season":"2024\/25","opposition":"London Cornish"},{"squad":"1st","date":"2024-09-21","team":"EGRFC","lineouts_won":7,"lineouts_total":9,"lineouts_success_rate":0.7777777778,"scrums_won":8,"scrums_total":8,"scrums_success_rate":1.0,"entries_22m":null,"points":24,"tries":null,"points_per_entry":null,"tries_per_entry":null,"game_id":"2024-09-21_1st_Haywards_Heath","season":"2024\/25","opposition":"Haywards Heath"},{"squad":"1st","date":"2024-09-21","team":"Opposition","lineouts_won":10,"lineouts_total":14,"lineouts_success_rate":0.7142857143,"scrums_won":9,"scrums_total":11,"scrums_success_rate":0.8181818182,"entries_22m":null,"points":19,"tries":null,"points_per_entry":null,"tries_per_entry":null,"game_id":"2024-09-21_1st_Haywards_Heath","season":"2024\/25","opposition":"Haywards Heath"},{"squad":"1st","date":"2024-10-12","team":"EGRFC","lineouts_won":7,"lineouts_total":11,"lineouts_success_rate":0.6363636364,"scrums_won":7,"scrums_total":7,"scrums_success_rate":1.0,"entries_22m":null,"points":21,"tries":null,"points_per_entry":null,"tries_per_entry":null,"game_id":"2024-10-12_1st_Hove","season":"2024\/25","opposition":"Hove"},{"squad":"1st","date":"2024-10-12","team":"Opposition","lineouts_won":9,"lineouts_total":12,"lineouts_success_rate":0.75,"scrums_won":6,"scrums_total":7,"scrums_success_rate":0.8571428571,"entries_22m":null,"points":34,"tries":null,"points_per_entry":null,"tries_per_entry":null,"game_id":"2024-10-12_1st_Hove","season":"2024\/25","opposition":"Hove"},{"squad":"1st","date":"2024-10-19","team":"EGRFC","lineouts_won":10,"lineouts_total":14,"lineouts_success_rate":0.7142857143,"scrums_won":5,"scrums_total":5,"scrums_success_rate":1.0,"entries_22m":null,"points":33,"tries":null,"points_per_entry":null,"tries_per_entry":null,"game_id":"2024-10-19_1st_Twickenham","season":"2024\/25","opposition":"Twickenham"},{"squad":"1st","date":"2024-10-19","team":"Opposition","lineouts_won":9,"lineouts_total":11,"lineouts_success_rate":0.8181818182,"scrums_won":6,"scrums_total":7,"scrums_success_rate":0.8571428571,"entries_22m":null,"points":41,"tries":null,"points_per_entry":null,"tries_per_entry":null,"game_id":"2024-10-19_1st_Twickenham","season":"2024\/25","opposition":"Twickenham"},{"squad":"1st","date":"2024-10-26","team":"EGRFC","lineouts_won":5,"lineouts_total":9,"lineouts_success_rate":0.5555555556,"scrums_won":6,"scrums_total":6,"scrums_success_rate":1.0,"entries_22m":null,"points":29,"tries":null,"points_per_entry":null,"tries_per_entry":null,"game_id":"2024-10-26_1st_KCS_Old_Boys","season":"2024\/25","opposition":"KCS Old Boys"},{"squad":"1st","date":"2024-10-26","team":"Opposition","lineouts_won":10,"lineouts_total":13,"lineouts_success_rate":0.7692307692,"scrums_won":8,"scrums_total":8,"scrums_success_rate":1.0,"entries_22m":null,"points":33,"tries":null,"points_per_entry":null,"tries_per_entry":null,"game_id":"2024-10-26_1st_KCS_Old_Boys","season":"2024\/25","opposition":"KCS Old Boys"},{"squad":"1st","date":"2024-11-09","team":"EGRFC","lineouts_won":3,"lineouts_total":8,"lineouts_success_rate":0.375,"scrums_won":5,"scrums_total":5,"scrums_success_rate":1.0,"entries_22m":null,"points":36,"tries":null,"points_per_entry":null,"tries_per_entry":null,"game_id":"2024-11-09_1st_Eastbourne","season":"2024\/25","opposition":"Eastbourne"},{"squad":"1st","date":"2024-11-09","team":"Opposition","lineouts_won":9,"lineouts_total":9,"lineouts_success_rate":1.0,"scrums_won":8,"scrums_total":8,"scrums_success_rate":1.0,"entries_22m":null,"points":33,"tries":null,"points_per_entry":null,"tries_per_entry":null,"game_id":"2024-11-09_1st_Eastbourne","season":"2024\/25","opposition":"Eastbourne"},{"squad":"1st","date":"2024-11-16","team":"EGRFC","lineouts_won":6,"lineouts_total":7,"lineouts_success_rate":0.8571428571,"scrums_won":10,"scrums_total":10,"scrums_success_rate":1.0,"entries_22m":null,"points":14,"tries":null,"points_per_entry":null,"tries_per_entry":null,"game_id":"2024-11-16_1st_Trinity","season":"2024\/25","opposition":"Trinity"},{"squad":"1st","date":"2024-11-16","team":"Opposition","lineouts_won":9,"lineouts_total":11,"lineouts_success_rate":0.8181818182,"scrums_won":2,"scrums_total":4,"scrums_success_rate":0.5,"entries_22m":null,"points":48,"tries":null,"points_per_entry":null,"tries_per_entry":null,"game_id":"2024-11-16_1st_Trinity","season":"2024\/25","opposition":"Trinity"},{"squad":"1st","date":"2024-11-23","team":"EGRFC","lineouts_won":14,"lineouts_total":18,"lineouts_success_rate":0.7777777778,"scrums_won":7,"scrums_total":7,"scrums_success_rate":1.0,"entries_22m":null,"points":19,"tries":null,"points_per_entry":null,"tries_per_entry":null,"game_id":"2024-11-23_1st_Old_Rutlishians","season":"2024\/25","opposition":"Old Rutlishians"},{"squad":"1st","date":"2024-11-23","team":"Opposition","lineouts_won":10,"lineouts_total":13,"lineouts_success_rate":0.7692307692,"scrums_won":3,"scrums_total":5,"scrums_success_rate":0.6,"entries_22m":null,"points":23,"tries":null,"points_per_entry":null,"tries_per_entry":null,"game_id":"2024-11-23_1st_Old_Rutlishians","season":"2024\/25","opposition":"Old Rutlishians"},{"squad":"1st","date":"2024-12-07","team":"EGRFC","lineouts_won":9,"lineouts_total":13,"lineouts_success_rate":0.6923076923,"scrums_won":13,"scrums_total":13,"scrums_success_rate":1.0,"entries_22m":null,"points":7,"tries":null,"points_per_entry":null,"tries_per_entry":null,"game_id":"2024-12-07_1st_Cobham","season":"2024\/25","opposition":"Cobham"},{"squad":"1st","date":"2024-12-07","team":"Opposition","lineouts_won":8,"lineouts_total":10,"lineouts_success_rate":0.8,"scrums_won":8,"scrums_total":10,"scrums_success_rate":0.8,"entries_22m":null,"points":26,"tries":null,"points_per_entry":null,"tries_per_entry":null,"game_id":"2024-12-07_1st_Cobham","season":"2024\/25","opposition":"Cobham"},{"squad":"1st","date":"2024-12-14","team":"EGRFC","lineouts_won":6,"lineouts_total":10,"lineouts_success_rate":0.6,"scrums_won":11,"scrums_total":11,"scrums_success_rate":1.0,"entries_22m":6,"points":18,"tries":2,"points_per_entry":3.0,"tries_per_entry":0.3333333333,"game_id":"2024-12-14_1st_Old_Haileyburians","season":"2024\/25","opposition":"Old Haileyburians"},{"squad":"1st","date":"2024-12-14","team":"Opposition","lineouts_won":16,"lineouts_total":17,"lineouts_success_rate":0.9411764706,"scrums_won":4,"scrums_total":5,"scrums_success_rate":0.8,"entries_22m":5,"points":5,"tries":1,"points_per_entry":1.0,"tries_per_entry":0.2,"game_id":"2024-12-14_1st_Old_Haileyburians","season":"2024\/25","opposition":"Old Haileyburians"},{"squad":"1st","date":"2025-01-04","team":"EGRFC","lineouts_won":10,"lineouts_total":17,"lineouts_success_rate":0.5882352941,"scrums_won":9,"scrums_total":9,"scrums_success_rate":1.0,"entries_22m":null,"points":14,"tries":null,"points_per_entry":null,"tries_per_entry":null,"game_id":"2025-01-04_1st_Weybridge_Vandals","season":"2024\/25","opposition":"Weybridge Vandals"},{"squad":"1st","date":"2025-01-04","team":"Opposition","lineouts_won":7,"lineouts_total":8,"lineouts_success_rate":0.875,"scrums_won":4,"scrums_total":8,"scrums_success_rate":0.5,"entries_22m":null,"points":20,"tries":null,"points_per_entry":null,"tries_per_entry":null,"game_id":"2025-01-04_1st_Weybridge_Vandals","season":"2024\/25","opposition":"Weybridge Vandals"},{"squad":"1st","date":"2025-01-18","team":"EGRFC","lineouts_won":7,"lineouts_total":10,"lineouts_success_rate":0.7,"scrums_won":11,"scrums_total":11,"scrums_success_rate":1.0,"entries_22m":null,"points":10,"tries":null,"points_per_entry":null,"tries_per_entry":null,"game_id":"2025-01-18_1st_Twickenham","season":"2024\/25","opposition":"Twickenham"},{"squad":"1st","date":"2025-01-18","team":"Opposition","lineouts_won":12,"lineouts_total":13,"lineouts_success_rate":0.9230769231,"scrums_won":5,"scrums_total":7,"scrums_success_rate":0.7142857143,"entries_22m":null,"points":47,"tries":null,"points_per_entry":null,"tries_per_entry":null,"game_id":"2025-01-18_1st_Twickenham","season":"2024\/25","opposition":"Twickenham"},{"squad":"1st","date":"2025-02-08","team":"EGRFC","lineouts_won":5,"lineouts_total":8,"lineouts_success_rate":0.625,"scrums_won":12,"scrums_total":12,"scrums_success_rate":1.0,"entries_22m":null,"points":11,"tries":null,"points_per_entry":null,"tries_per_entry":null,"game_id":"2025-02-08_1st_Hove","season":"2024\/25","opposition":"Hove"},{"squad":"1st","date":"2025-02-08","team":"Opposition","lineouts_won":8,"lineouts_total":10,"lineouts_success_rate":0.8,"scrums_won":7,"scrums_total":7,"scrums_success_rate":1.0,"entries_22m":null,"points":18,"tries":null,"points_per_entry":null,"tries_per_entry":null,"game_id":"2025-02-08_1st_Hove","season":"2024\/25","opposition":"Hove"},{"squad":"1st","date":"2025-02-15","team":"EGRFC","lineouts_won":12,"lineouts_total":14,"lineouts_success_rate":0.8571428571,"scrums_won":7,"scrums_total":7,"scrums_success_rate":1.0,"entries_22m":5,"points":14,"tries":2,"points_per_entry":2.8,"tries_per_entry":0.4,"game_id":"2025-02-15_1st_Eastbourne","season":"2024\/25","opposition":"Eastbourne"},{"squad":"1st","date":"2025-02-15","team":"Opposition","lineouts_won":12,"lineouts_total":13,"lineouts_success_rate":0.9230769231,"scrums_won":7,"scrums_total":7,"scrums_success_rate":1.0,"entries_22m":7,"points":15,"tries":2,"points_per_entry":2.1,"tries_per_entry":0.2857142857,"game_id":"2025-02-15_1st_Eastbourne","season":"2024\/25","opposition":"Eastbourne"},{"squad":"1st","date":"2025-03-01","team":"EGRFC","lineouts_won":9,"lineouts_total":11,"lineouts_success_rate":0.8181818182,"scrums_won":11,"scrums_total":11,"scrums_success_rate":1.0,"entries_22m":null,"points":18,"tries":null,"points_per_entry":null,"tries_per_entry":null,"game_id":"2025-03-01_1st_Trinity","season":"2024\/25","opposition":"Trinity"},{"squad":"1st","date":"2025-03-01","team":"Opposition","lineouts_won":9,"lineouts_total":11,"lineouts_success_rate":0.8181818182,"scrums_won":3,"scrums_total":4,"scrums_success_rate":0.75,"entries_22m":null,"points":34,"tries":null,"points_per_entry":null,"tries_per_entry":null,"game_id":"2025-03-01_1st_Trinity","season":"2024\/25","opposition":"Trinity"},{"squad":"1st","date":"2025-03-08","team":"EGRFC","lineouts_won":11,"lineouts_total":14,"lineouts_success_rate":0.7857142857,"scrums_won":10,"scrums_total":11,"scrums_success_rate":0.9090909091,"entries_22m":null,"points":14,"tries":null,"points_per_entry":null,"tries_per_entry":null,"game_id":"2025-03-08_1st_Old_Rutlishians","season":"2024\/25","opposition":"Old Rutlishians"},{"squad":"1st","date":"2025-03-08","team":"Opposition","lineouts_won":5,"lineouts_total":8,"lineouts_success_rate":0.625,"scrums_won":2,"scrums_total":3,"scrums_success_rate":0.6666666667,"entries_22m":null,"points":71,"tries":null,"points_per_entry":null,"tries_per_entry":null,"game_id":"2025-03-08_1st_Old_Rutlishians","season":"2024\/25","opposition":"Old Rutlishians"},{"squad":"1st","date":"2025-03-22","team":"EGRFC","lineouts_won":15,"lineouts_total":20,"lineouts_success_rate":0.75,"scrums_won":5,"scrums_total":6,"scrums_success_rate":0.8333333333,"entries_22m":9,"points":21,"tries":3,"points_per_entry":2.3,"tries_per_entry":0.3333333333,"game_id":"2025-03-22_1st_Cobham","season":"2024\/25","opposition":"Cobham"},{"squad":"1st","date":"2025-03-22","team":"Opposition","lineouts_won":11,"lineouts_total":13,"lineouts_success_rate":0.8461538462,"scrums_won":3,"scrums_total":5,"scrums_success_rate":0.6,"entries_22m":11,"points":43,"tries":7,"points_per_entry":3.9,"tries_per_entry":0.6363636364,"game_id":"2025-03-22_1st_Cobham","season":"2024\/25","opposition":"Cobham"},{"squad":"1st","date":"2025-04-12","team":"EGRFC","lineouts_won":10,"lineouts_total":11,"lineouts_success_rate":0.9090909091,"scrums_won":5,"scrums_total":6,"scrums_success_rate":0.8333333333,"entries_22m":9,"points":45,"tries":6,"points_per_entry":5.0,"tries_per_entry":0.6666666667,"game_id":"2025-04-12_1st_Haywards_Heath","season":"2024\/25","opposition":"Haywards Heath"},{"squad":"1st","date":"2025-04-12","team":"Opposition","lineouts_won":2,"lineouts_total":9,"lineouts_success_rate":0.2222222222,"scrums_won":7,"scrums_total":7,"scrums_success_rate":1.0,"entries_22m":10,"points":37,"tries":6,"points_per_entry":3.7,"tries_per_entry":0.6,"game_id":"2025-04-12_1st_Haywards_Heath","season":"2024\/25","opposition":"Haywards Heath"},{"squad":"1st","date":"2025-08-23","team":"EGRFC","lineouts_won":6,"lineouts_total":9,"lineouts_success_rate":0.6666666667,"scrums_won":11,"scrums_total":11,"scrums_success_rate":1.0,"entries_22m":null,"points":19,"tries":null,"points_per_entry":null,"tries_per_entry":null,"game_id":"2025-08-23_1st_Beccehamians","season":"2025\/26","opposition":"Beccehamians"},{"squad":"1st","date":"2025-08-23","team":"Opposition","lineouts_won":9,"lineouts_total":14,"lineouts_success_rate":0.6428571429,"scrums_won":11,"scrums_total":11,"scrums_success_rate":1.0,"entries_22m":null,"points":24,"tries":null,"points_per_entry":null,"tries_per_entry":null,"game_id":"2025-08-23_1st_Beccehamians","season":"2025\/26","opposition":"Beccehamians"},{"squad":"1st","date":"2025-10-04","team":"EGRFC","lineouts_won":12,"lineouts_total":12,"lineouts_success_rate":1.0,"scrums_won":17,"scrums_total":17,"scrums_success_rate":1.0,"entries_22m":8,"points":27,"tries":4,"points_per_entry":3.4,"tries_per_entry":0.5,"game_id":"2025-10-04_1st_Seaford","season":"2025\/26","opposition":"Seaford"},{"squad":"1st","date":"2025-10-04","team":"Opposition","lineouts_won":7,"lineouts_total":7,"lineouts_success_rate":1.0,"scrums_won":11,"scrums_total":12,"scrums_success_rate":0.9166666667,"entries_22m":5,"points":10,"tries":2,"points_per_entry":2.0,"tries_per_entry":0.4,"game_id":"2025-10-04_1st_Seaford","season":"2025\/26","opposition":"Seaford"},{"squad":"1st","date":"2025-10-11","team":"EGRFC","lineouts_won":6,"lineouts_total":6,"lineouts_success_rate":1.0,"scrums_won":8,"scrums_total":8,"scrums_success_rate":1.0,"entries_22m":12,"points":69,"tries":11,"points_per_entry":5.8,"tries_per_entry":0.9166666667,"game_id":"2025-10-11_1st_Shoreham","season":"2025\/26","opposition":"Shoreham"},{"squad":"1st","date":"2025-10-11","team":"Opposition","lineouts_won":3,"lineouts_total":7,"lineouts_success_rate":0.4285714286,"scrums_won":6,"scrums_total":11,"scrums_success_rate":0.5454545455,"entries_22m":4,"points":12,"tries":2,"points_per_entry":3.0,"tries_per_entry":0.5,"game_id":"2025-10-11_1st_Shoreham","season":"2025\/26","opposition":"Shoreham"},{"squad":"1st","date":"2025-11-08","team":"EGRFC","lineouts_won":9,"lineouts_total":10,"lineouts_success_rate":0.9,"scrums_won":10,"scrums_total":10,"scrums_success_rate":1.0,"entries_22m":11,"points":43,"tries":7,"points_per_entry":3.9,"tries_per_entry":0.6363636364,"game_id":"2025-11-08_1st_Lewes","season":"2025\/26","opposition":"Lewes"},{"squad":"1st","date":"2025-11-08","team":"Opposition","lineouts_won":3,"lineouts_total":10,"lineouts_success_rate":0.3,"scrums_won":5,"scrums_total":7,"scrums_success_rate":0.7142857143,"entries_22m":4,"points":14,"tries":2,"points_per_entry":3.5,"tries_per_entry":0.5,"game_id":"2025-11-08_1st_Lewes","season":"2025\/26","opposition":"Lewes"},{"squad":"1st","date":"2025-11-15","team":"EGRFC","lineouts_won":7,"lineouts_total":11,"lineouts_success_rate":0.6363636364,"scrums_won":11,"scrums_total":12,"scrums_success_rate":0.9166666667,"entries_22m":10,"points":15,"tries":2,"points_per_entry":1.5,"tries_per_entry":0.2,"game_id":"2025-11-15_1st_Hove","season":"2025\/26","opposition":"Hove"},{"squad":"1st","date":"2025-11-15","team":"Opposition","lineouts_won":12,"lineouts_total":15,"lineouts_success_rate":0.8,"scrums_won":6,"scrums_total":7,"scrums_success_rate":0.8571428571,"entries_22m":12,"points":32,"tries":5,"points_per_entry":2.7,"tries_per_entry":0.4166666667,"game_id":"2025-11-15_1st_Hove","season":"2025\/26","opposition":"Hove"},{"squad":"1st","date":"2025-11-22","team":"EGRFC","lineouts_won":15,"lineouts_total":17,"lineouts_success_rate":0.8823529412,"scrums_won":6,"scrums_total":6,"scrums_success_rate":1.0,"entries_22m":5,"points":5,"tries":1,"points_per_entry":1.0,"tries_per_entry":0.2,"game_id":"2025-11-22_1st_Pulborough","season":"2025\/26","opposition":"Pulborough"},{"squad":"1st","date":"2025-11-22","team":"Opposition","lineouts_won":5,"lineouts_total":8,"lineouts_success_rate":0.625,"scrums_won":4,"scrums_total":6,"scrums_success_rate":0.6666666667,"entries_22m":9,"points":12,"tries":2,"points_per_entry":1.3,"tries_per_entry":0.2222222222,"game_id":"2025-11-22_1st_Pulborough","season":"2025\/26","opposition":"Pulborough"},{"squad":"1st","date":"2025-11-29","team":"EGRFC","lineouts_won":11,"lineouts_total":14,"lineouts_success_rate":0.7857142857,"scrums_won":5,"scrums_total":5,"scrums_success_rate":1.0,"entries_22m":13,"points":56,"tries":10,"points_per_entry":4.3,"tries_per_entry":0.7692307692,"game_id":"2025-11-29_1st_Eastbourne","season":"2025\/26","opposition":"Eastbourne II"},{"squad":"1st","date":"2025-11-29","team":"Opposition","lineouts_won":9,"lineouts_total":12,"lineouts_success_rate":0.75,"scrums_won":5,"scrums_total":7,"scrums_success_rate":0.7142857143,"entries_22m":3,"points":0,"tries":0,"points_per_entry":0.0,"tries_per_entry":0.0,"game_id":"2025-11-29_1st_Eastbourne","season":"2025\/26","opposition":"Eastbourne II"},{"squad":"1st","date":"2025-12-20","team":"EGRFC","lineouts_won":4,"lineouts_total":6,"lineouts_success_rate":0.6666666667,"scrums_won":2,"scrums_total":2,"scrums_success_rate":1.0,"entries_22m":11,"points":29,"tries":5,"points_per_entry":2.6,"tries_per_entry":0.4545454545,"game_id":"2025-12-20_1st_Ditchling","season":"2025\/26","opposition":"Ditchling"},{"squad":"1st","date":"2025-12-20","team":"Opposition","lineouts_won":10,"lineouts_total":14,"lineouts_success_rate":0.7142857143,"scrums_won":0,"scrums_total":3,"scrums_success_rate":0.0,"entries_22m":9,"points":19,"tries":3,"points_per_entry":2.1,"tries_per_entry":0.3333333333,"game_id":"2025-12-20_1st_Ditchling","season":"2025\/26","opposition":"Ditchling"},{"squad":"1st","date":"2026-01-10","team":"EGRFC","lineouts_won":7,"lineouts_total":10,"lineouts_success_rate":0.7,"scrums_won":8,"scrums_total":8,"scrums_success_rate":1.0,"entries_22m":10,"points":41,"tries":7,"points_per_entry":4.1,"tries_per_entry":0.7,"game_id":"2026-01-10_1st_Royals","season":"2025\/26","opposition":"Royals"},{"squad":"1st","date":"2026-01-10","team":"Opposition","lineouts_won":13,"lineouts_total":15,"lineouts_success_rate":0.8666666667,"scrums_won":3,"scrums_total":5,"scrums_success_rate":0.6,"entries_22m":4,"points":5,"tries":1,"points_per_entry":1.3,"tries_per_entry":0.25,"game_id":"2026-01-10_1st_Royals","season":"2025\/26","opposition":"Royals"},{"squad":"1st","date":"2026-01-24","team":"EGRFC","lineouts_won":5,"lineouts_total":6,"lineouts_success_rate":0.8333333333,"scrums_won":13,"scrums_total":13,"scrums_success_rate":1.0,"entries_22m":3,"points":0,"tries":0,"points_per_entry":0.0,"tries_per_entry":0.0,"game_id":"2026-01-24_1st_Brighton","season":"2025\/26","opposition":"Brighton II"},{"squad":"1st","date":"2026-01-24","team":"Opposition","lineouts_won":6,"lineouts_total":9,"lineouts_success_rate":0.6666666667,"scrums_won":9,"scrums_total":9,"scrums_success_rate":1.0,"entries_22m":15,"points":50,"tries":8,"points_per_entry":3.3,"tries_per_entry":0.5333333333,"game_id":"2026-01-24_1st_Brighton","season":"2025\/26","opposition":"Brighton II"},{"squad":"1st","date":"2026-02-14","team":"EGRFC","lineouts_won":11,"lineouts_total":12,"lineouts_success_rate":0.9166666667,"scrums_won":8,"scrums_total":8,"scrums_success_rate":1.0,"entries_22m":11,"points":39,"tries":6,"points_per_entry":3.5,"tries_per_entry":0.5454545455,"game_id":"2026-02-14_1st_Lewes","season":"2025\/26","opposition":"Lewes"},{"squad":"1st","date":"2026-02-14","team":"Opposition","lineouts_won":4,"lineouts_total":10,"lineouts_success_rate":0.4,"scrums_won":4,"scrums_total":7,"scrums_success_rate":0.5714285714,"entries_22m":6,"points":22,"tries":3,"points_per_entry":3.7,"tries_per_entry":0.5,"game_id":"2026-02-14_1st_Lewes","season":"2025\/26","opposition":"Lewes"},{"squad":"1st","date":"2026-02-28","team":"EGRFC","lineouts_won":12,"lineouts_total":13,"lineouts_success_rate":0.9230769231,"scrums_won":6,"scrums_total":6,"scrums_success_rate":1.0,"entries_22m":8,"points":14,"tries":1,"points_per_entry":1.8,"tries_per_entry":0.125,"game_id":"2026-02-28_1st_Pulborough","season":"2025\/26","opposition":"Pulborough"},{"squad":"1st","date":"2026-02-28","team":"Opposition","lineouts_won":6,"lineouts_total":15,"lineouts_success_rate":0.4,"scrums_won":4,"scrums_total":7,"scrums_success_rate":0.5714285714,"entries_22m":5,"points":13,"tries":2,"points_per_entry":2.6,"tries_per_entry":0.4,"game_id":"2026-02-28_1st_Pulborough","season":"2025\/26","opposition":"Pulborough"},{"squad":"1st","date":"2026-03-07","team":"EGRFC","lineouts_won":10,"lineouts_total":13,"lineouts_success_rate":0.7692307692,"scrums_won":8,"scrums_total":10,"scrums_success_rate":0.8,"entries_22m":6,"points":29,"tries":5,"points_per_entry":4.8,"tries_per_entry":0.8333333333,"game_id":"2026-03-07_1st_Eastbourne","season":"2025\/26","opposition":"Eastbourne II"},{"squad":"1st","date":"2026-03-07","team":"Opposition","lineouts_won":11,"lineouts_total":13,"lineouts_success_rate":0.8461538462,"scrums_won":11,"scrums_total":13,"scrums_success_rate":0.8461538462,"entries_22m":10,"points":0,"tries":0,"points_per_entry":0.0,"tries_per_entry":0.0,"game_id":"2026-03-07_1st_Eastbourne","season":"2025\/26","opposition":"Eastbourne II"},{"squad":"1st","date":"2026-03-21","team":"EGRFC","lineouts_won":5,"lineouts_total":5,"lineouts_success_rate":1.0,"scrums_won":4,"scrums_total":5,"scrums_success_rate":0.8,"entries_22m":20,"points":118,"tries":18,"points_per_entry":5.9,"tries_per_entry":0.9,"game_id":"2026-03-21_1st_Crawley","season":"2025\/26","opposition":"Crawley"},{"squad":"1st","date":"2026-03-21","team":"Opposition","lineouts_won":8,"lineouts_total":13,"lineouts_success_rate":0.6153846154,"scrums_won":6,"scrums_total":7,"scrums_success_rate":0.8571428571,"entries_22m":5,"points":14,"tries":2,"points_per_entry":2.8,"tries_per_entry":0.4,"game_id":"2026-03-21_1st_Crawley","season":"2025\/26","opposition":"Crawley"},{"squad":"1st","date":"2026-03-28","team":"EGRFC","lineouts_won":11,"lineouts_total":14,"lineouts_success_rate":0.7857142857,"scrums_won":8,"scrums_total":8,"scrums_success_rate":1.0,"entries_22m":11,"points":27,"tries":4,"points_per_entry":2.5,"tries_per_entry":0.3636363636,"game_id":"2026-03-28_1st_Ditchling","season":"2025\/26","opposition":"Ditchling"},{"squad":"1st","date":"2026-03-28","team":"Opposition","lineouts_won":11,"lineouts_total":16,"lineouts_success_rate":0.6875,"scrums_won":7,"scrums_total":9,"scrums_success_rate":0.7777777778,"entries_22m":5,"points":3,"tries":0,"points_per_entry":0.6,"tries_per_entry":0.0,"game_id":"2026-03-28_1st_Ditchling","season":"2025\/26","opposition":"Ditchling"},{"squad":"1st","date":"2026-04-11","team":"EGRFC","lineouts_won":11,"lineouts_total":12,"lineouts_success_rate":0.9166666667,"scrums_won":6,"scrums_total":6,"scrums_success_rate":1.0,"entries_22m":10,"points":45,"tries":7,"points_per_entry":4.5,"tries_per_entry":0.7,"game_id":"2026-04-11_1st_Royals","season":"2025\/26","opposition":"Royals"},{"squad":"1st","date":"2026-04-11","team":"Opposition","lineouts_won":7,"lineouts_total":11,"lineouts_success_rate":0.6363636364,"scrums_won":1,"scrums_total":3,"scrums_success_rate":0.3333333333,"entries_22m":6,"points":27,"tries":4,"points_per_entry":4.5,"tries_per_entry":0.6666666667,"game_id":"2026-04-11_1st_Royals","season":"2025\/26","opposition":"Royals"},{"squad":"1st","date":"2026-04-18","team":"EGRFC","lineouts_won":10,"lineouts_total":14,"lineouts_success_rate":0.7142857143,"scrums_won":6,"scrums_total":6,"scrums_success_rate":1.0,"entries_22m":9,"points":40,"tries":6,"points_per_entry":4.4,"tries_per_entry":0.6666666667,"game_id":"2026-04-18_1st_Seaford","season":"2025\/26","opposition":"Seaford"},{"squad":"1st","date":"2026-04-18","team":"Opposition","lineouts_won":5,"lineouts_total":7,"lineouts_success_rate":0.7142857143,"scrums_won":8,"scrums_total":9,"scrums_success_rate":0.8888888889,"entries_22m":6,"points":27,"tries":5,"points_per_entry":4.5,"tries_per_entry":0.8333333333,"game_id":"2026-04-18_1st_Seaford","season":"2025\/26","opposition":"Seaford"},{"squad":"2nd","date":"2021-09-25","team":"EGRFC","lineouts_won":11,"lineouts_total":14,"lineouts_success_rate":0.7857142857,"scrums_won":10,"scrums_total":13,"scrums_success_rate":0.7692307692,"entries_22m":null,"points":12,"tries":null,"points_per_entry":null,"tries_per_entry":null,"game_id":"2021-09-25_2nd_Worthing","season":"2021\/22","opposition":"Worthing"},{"squad":"2nd","date":"2021-09-25","team":"Opposition","lineouts_won":5,"lineouts_total":8,"lineouts_success_rate":0.625,"scrums_won":7,"scrums_total":9,"scrums_success_rate":0.7777777778,"entries_22m":null,"points":31,"tries":null,"points_per_entry":null,"tries_per_entry":null,"game_id":"2021-09-25_2nd_Worthing","season":"2021\/22","opposition":"Worthing"},{"squad":"2nd","date":"2021-10-09","team":"EGRFC","lineouts_won":8,"lineouts_total":11,"lineouts_success_rate":0.7272727273,"scrums_won":11,"scrums_total":11,"scrums_success_rate":1.0,"entries_22m":null,"points":24,"tries":null,"points_per_entry":null,"tries_per_entry":null,"game_id":"2021-10-09_2nd_Royals","season":"2021\/22","opposition":"Royals"},{"squad":"2nd","date":"2021-10-09","team":"Opposition","lineouts_won":8,"lineouts_total":14,"lineouts_success_rate":0.5714285714,"scrums_won":2,"scrums_total":6,"scrums_success_rate":0.3333333333,"entries_22m":null,"points":27,"tries":null,"points_per_entry":null,"tries_per_entry":null,"game_id":"2021-10-09_2nd_Royals","season":"2021\/22","opposition":"Royals"},{"squad":"2nd","date":"2021-12-11","team":"EGRFC","lineouts_won":8,"lineouts_total":11,"lineouts_success_rate":0.7272727273,"scrums_won":6,"scrums_total":6,"scrums_success_rate":1.0,"entries_22m":null,"points":25,"tries":null,"points_per_entry":null,"tries_per_entry":null,"game_id":"2021-12-11_2nd_Crowborough","season":"2021\/22","opposition":"Crowborough"},{"squad":"2nd","date":"2021-12-11","team":"Opposition","lineouts_won":4,"lineouts_total":7,"lineouts_success_rate":0.5714285714,"scrums_won":13,"scrums_total":13,"scrums_success_rate":1.0,"entries_22m":null,"points":5,"tries":null,"points_per_entry":null,"tries_per_entry":null,"game_id":"2021-12-11_2nd_Crowborough","season":"2021\/22","opposition":"Crowborough"},{"squad":"2nd","date":"2022-01-15","team":"EGRFC","lineouts_won":11,"lineouts_total":15,"lineouts_success_rate":0.7333333333,"scrums_won":5,"scrums_total":9,"scrums_success_rate":0.5555555556,"entries_22m":null,"points":20,"tries":null,"points_per_entry":null,"tries_per_entry":null,"game_id":"2022-01-15_2nd_Rye","season":"2021\/22","opposition":"Rye"},{"squad":"2nd","date":"2022-01-15","team":"Opposition","lineouts_won":6,"lineouts_total":9,"lineouts_success_rate":0.6666666667,"scrums_won":7,"scrums_total":8,"scrums_success_rate":0.875,"entries_22m":null,"points":12,"tries":null,"points_per_entry":null,"tries_per_entry":null,"game_id":"2022-01-15_2nd_Rye","season":"2021\/22","opposition":"Rye"},{"squad":"2nd","date":"2022-01-29","team":"EGRFC","lineouts_won":10,"lineouts_total":11,"lineouts_success_rate":0.9090909091,"scrums_won":5,"scrums_total":5,"scrums_success_rate":1.0,"entries_22m":null,"points":23,"tries":null,"points_per_entry":null,"tries_per_entry":null,"game_id":"2022-01-29_2nd_Crawley","season":"2021\/22","opposition":"Crawley"},{"squad":"2nd","date":"2022-01-29","team":"Opposition","lineouts_won":6,"lineouts_total":16,"lineouts_success_rate":0.375,"scrums_won":10,"scrums_total":12,"scrums_success_rate":0.8333333333,"entries_22m":null,"points":13,"tries":null,"points_per_entry":null,"tries_per_entry":null,"game_id":"2022-01-29_2nd_Crawley","season":"2021\/22","opposition":"Crawley"},{"squad":"2nd","date":"2022-03-05","team":"EGRFC","lineouts_won":7,"lineouts_total":12,"lineouts_success_rate":0.5833333333,"scrums_won":5,"scrums_total":6,"scrums_success_rate":0.8333333333,"entries_22m":null,"points":22,"tries":null,"points_per_entry":null,"tries_per_entry":null,"game_id":"2022-03-05_2nd_Horsham","season":"2021\/22","opposition":"Horsham"},{"squad":"2nd","date":"2022-03-05","team":"Opposition","lineouts_won":9,"lineouts_total":12,"lineouts_success_rate":0.75,"scrums_won":15,"scrums_total":15,"scrums_success_rate":1.0,"entries_22m":null,"points":0,"tries":null,"points_per_entry":null,"tries_per_entry":null,"game_id":"2022-03-05_2nd_Horsham","season":"2021\/22","opposition":"Horsham"},{"squad":"2nd","date":"2022-03-12","team":"EGRFC","lineouts_won":9,"lineouts_total":12,"lineouts_success_rate":0.75,"scrums_won":8,"scrums_total":10,"scrums_success_rate":0.8,"entries_22m":null,"points":32,"tries":null,"points_per_entry":null,"tries_per_entry":null,"game_id":"2022-03-12_2nd_Rye","season":"2021\/22","opposition":"Rye"},{"squad":"2nd","date":"2022-03-12","team":"Opposition","lineouts_won":9,"lineouts_total":14,"lineouts_success_rate":0.6428571429,"scrums_won":6,"scrums_total":6,"scrums_success_rate":1.0,"entries_22m":null,"points":10,"tries":null,"points_per_entry":null,"tries_per_entry":null,"game_id":"2022-03-12_2nd_Rye","season":"2021\/22","opposition":"Rye"},{"squad":"2nd","date":"2022-04-16","team":"EGRFC","lineouts_won":10,"lineouts_total":10,"lineouts_success_rate":1.0,"scrums_won":4,"scrums_total":4,"scrums_success_rate":1.0,"entries_22m":null,"points":46,"tries":null,"points_per_entry":null,"tries_per_entry":null,"game_id":"2022-04-16_2nd_St_Francis","season":"2021\/22","opposition":"St Francis"},{"squad":"2nd","date":"2022-04-16","team":"Opposition","lineouts_won":4,"lineouts_total":5,"lineouts_success_rate":0.8,"scrums_won":12,"scrums_total":12,"scrums_success_rate":1.0,"entries_22m":null,"points":24,"tries":null,"points_per_entry":null,"tries_per_entry":null,"game_id":"2022-04-16_2nd_St_Francis","season":"2021\/22","opposition":"St Francis"},{"squad":"2nd","date":"2022-10-15","team":"EGRFC","lineouts_won":11,"lineouts_total":14,"lineouts_success_rate":0.7857142857,"scrums_won":4,"scrums_total":4,"scrums_success_rate":1.0,"entries_22m":null,"points":21,"tries":null,"points_per_entry":null,"tries_per_entry":null,"game_id":"2022-10-15_2nd_Eastbourne","season":"2022\/23","opposition":"Eastbourne"},{"squad":"2nd","date":"2022-10-15","team":"Opposition","lineouts_won":8,"lineouts_total":9,"lineouts_success_rate":0.8888888889,"scrums_won":8,"scrums_total":8,"scrums_success_rate":1.0,"entries_22m":null,"points":20,"tries":null,"points_per_entry":null,"tries_per_entry":null,"game_id":"2022-10-15_2nd_Eastbourne","season":"2022\/23","opposition":"Eastbourne"},{"squad":"2nd","date":"2022-10-29","team":"EGRFC","lineouts_won":11,"lineouts_total":17,"lineouts_success_rate":0.6470588235,"scrums_won":10,"scrums_total":11,"scrums_success_rate":0.9090909091,"entries_22m":null,"points":17,"tries":null,"points_per_entry":null,"tries_per_entry":null,"game_id":"2022-10-29_2nd_St_Francis","season":"2022\/23","opposition":"St Francis"},{"squad":"2nd","date":"2022-10-29","team":"Opposition","lineouts_won":3,"lineouts_total":6,"lineouts_success_rate":0.5,"scrums_won":8,"scrums_total":8,"scrums_success_rate":1.0,"entries_22m":null,"points":17,"tries":null,"points_per_entry":null,"tries_per_entry":null,"game_id":"2022-10-29_2nd_St_Francis","season":"2022\/23","opposition":"St Francis"},{"squad":"2nd","date":"2023-01-28","team":"EGRFC","lineouts_won":8,"lineouts_total":11,"lineouts_success_rate":0.7272727273,"scrums_won":9,"scrums_total":9,"scrums_success_rate":1.0,"entries_22m":null,"points":19,"tries":null,"points_per_entry":null,"tries_per_entry":null,"game_id":"2023-01-28_2nd_St_Francis","season":"2022\/23","opposition":"St Francis"},{"squad":"2nd","date":"2023-01-28","team":"Opposition","lineouts_won":2,"lineouts_total":3,"lineouts_success_rate":0.6666666667,"scrums_won":4,"scrums_total":5,"scrums_success_rate":0.8,"entries_22m":null,"points":38,"tries":null,"points_per_entry":null,"tries_per_entry":null,"game_id":"2023-01-28_2nd_St_Francis","season":"2022\/23","opposition":"St Francis"},{"squad":"2nd","date":"2023-09-09","team":"EGRFC","lineouts_won":12,"lineouts_total":12,"lineouts_success_rate":1.0,"scrums_won":6,"scrums_total":9,"scrums_success_rate":0.6666666667,"entries_22m":null,"points":32,"tries":null,"points_per_entry":null,"tries_per_entry":null,"game_id":"2023-09-09_2nd_Uckfield","season":"2023\/24","opposition":"Uckfield"},{"squad":"2nd","date":"2023-09-09","team":"Opposition","lineouts_won":5,"lineouts_total":9,"lineouts_success_rate":0.5555555556,"scrums_won":9,"scrums_total":10,"scrums_success_rate":0.9,"entries_22m":null,"points":26,"tries":null,"points_per_entry":null,"tries_per_entry":null,"game_id":"2023-09-09_2nd_Uckfield","season":"2023\/24","opposition":"Uckfield"},{"squad":"2nd","date":"2023-09-16","team":"EGRFC","lineouts_won":6,"lineouts_total":6,"lineouts_success_rate":1.0,"scrums_won":6,"scrums_total":8,"scrums_success_rate":0.75,"entries_22m":null,"points":63,"tries":null,"points_per_entry":null,"tries_per_entry":null,"game_id":"2023-09-16_2nd_Shoreham","season":"2023\/24","opposition":"Shoreham"},{"squad":"2nd","date":"2023-09-16","team":"Opposition","lineouts_won":9,"lineouts_total":11,"lineouts_success_rate":0.8181818182,"scrums_won":8,"scrums_total":9,"scrums_success_rate":0.8888888889,"entries_22m":null,"points":0,"tries":null,"points_per_entry":null,"tries_per_entry":null,"game_id":"2023-09-16_2nd_Shoreham","season":"2023\/24","opposition":"Shoreham"},{"squad":"2nd","date":"2023-09-23","team":"EGRFC","lineouts_won":11,"lineouts_total":12,"lineouts_success_rate":0.9166666667,"scrums_won":4,"scrums_total":5,"scrums_success_rate":0.8,"entries_22m":null,"points":52,"tries":null,"points_per_entry":null,"tries_per_entry":null,"game_id":"2023-09-23_2nd_Holbrook","season":"2023\/24","opposition":"Holbrook"},{"squad":"2nd","date":"2023-09-23","team":"Opposition","lineouts_won":13,"lineouts_total":13,"lineouts_success_rate":1.0,"scrums_won":10,"scrums_total":10,"scrums_success_rate":1.0,"entries_22m":null,"points":19,"tries":null,"points_per_entry":null,"tries_per_entry":null,"game_id":"2023-09-23_2nd_Holbrook","season":"2023\/24","opposition":"Holbrook"},{"squad":"2nd","date":"2024-01-13","team":"EGRFC","lineouts_won":9,"lineouts_total":13,"lineouts_success_rate":0.6923076923,"scrums_won":4,"scrums_total":5,"scrums_success_rate":0.8,"entries_22m":null,"points":36,"tries":null,"points_per_entry":null,"tries_per_entry":null,"game_id":"2024-01-13_2nd_Shoreham","season":"2023\/24","opposition":"Shoreham"},{"squad":"2nd","date":"2024-01-13","team":"Opposition","lineouts_won":6,"lineouts_total":8,"lineouts_success_rate":0.75,"scrums_won":4,"scrums_total":4,"scrums_success_rate":1.0,"entries_22m":null,"points":14,"tries":null,"points_per_entry":null,"tries_per_entry":null,"game_id":"2024-01-13_2nd_Shoreham","season":"2023\/24","opposition":"Shoreham"},{"squad":"2nd","date":"2024-01-20","team":"EGRFC","lineouts_won":7,"lineouts_total":7,"lineouts_success_rate":1.0,"scrums_won":5,"scrums_total":8,"scrums_success_rate":0.625,"entries_22m":null,"points":20,"tries":null,"points_per_entry":null,"tries_per_entry":null,"game_id":"2024-01-20_2nd_Heathfield_&_Waldron","season":"2023\/24","opposition":"Heathfield & Waldron"},{"squad":"2nd","date":"2024-01-20","team":"Opposition","lineouts_won":3,"lineouts_total":8,"lineouts_success_rate":0.375,"scrums_won":7,"scrums_total":11,"scrums_success_rate":0.6363636364,"entries_22m":null,"points":10,"tries":null,"points_per_entry":null,"tries_per_entry":null,"game_id":"2024-01-20_2nd_Heathfield_&_Waldron","season":"2023\/24","opposition":"Heathfield & Waldron"},{"squad":"2nd","date":"2024-02-17","team":"EGRFC","lineouts_won":5,"lineouts_total":8,"lineouts_success_rate":0.625,"scrums_won":7,"scrums_total":7,"scrums_success_rate":1.0,"entries_22m":null,"points":48,"tries":null,"points_per_entry":null,"tries_per_entry":null,"game_id":"2024-02-17_2nd_Hellingly","season":"2023\/24","opposition":"Hellingly"},{"squad":"2nd","date":"2024-02-17","team":"Opposition","lineouts_won":2,"lineouts_total":6,"lineouts_success_rate":0.3333333333,"scrums_won":8,"scrums_total":10,"scrums_success_rate":0.8,"entries_22m":null,"points":14,"tries":null,"points_per_entry":null,"tries_per_entry":null,"game_id":"2024-02-17_2nd_Hellingly","season":"2023\/24","opposition":"Hellingly"},{"squad":"2nd","date":"2024-04-06","team":"EGRFC","lineouts_won":15,"lineouts_total":18,"lineouts_success_rate":0.8333333333,"scrums_won":5,"scrums_total":6,"scrums_success_rate":0.8333333333,"entries_22m":null,"points":29,"tries":null,"points_per_entry":null,"tries_per_entry":null,"game_id":"2024-04-06_2nd_Midhurst","season":"2023\/24","opposition":"Midhurst"},{"squad":"2nd","date":"2024-04-06","team":"Opposition","lineouts_won":5,"lineouts_total":8,"lineouts_success_rate":0.625,"scrums_won":4,"scrums_total":7,"scrums_success_rate":0.5714285714,"entries_22m":null,"points":17,"tries":null,"points_per_entry":null,"tries_per_entry":null,"game_id":"2024-04-06_2nd_Midhurst","season":"2023\/24","opposition":"Midhurst"},{"squad":"2nd","date":"2024-08-17","team":"EGRFC","lineouts_won":11,"lineouts_total":13,"lineouts_success_rate":0.8461538462,"scrums_won":7,"scrums_total":8,"scrums_success_rate":0.875,"entries_22m":null,"points":24,"tries":null,"points_per_entry":null,"tries_per_entry":null,"game_id":"2024-08-17_2nd_Warlingham","season":"2024\/25","opposition":"Warlingham"},{"squad":"2nd","date":"2024-08-17","team":"Opposition","lineouts_won":6,"lineouts_total":10,"lineouts_success_rate":0.6,"scrums_won":9,"scrums_total":10,"scrums_success_rate":0.9,"entries_22m":null,"points":21,"tries":null,"points_per_entry":null,"tries_per_entry":null,"game_id":"2024-08-17_2nd_Warlingham","season":"2024\/25","opposition":"Warlingham"},{"squad":"2nd","date":"2024-10-26","team":"EGRFC","lineouts_won":4,"lineouts_total":6,"lineouts_success_rate":0.6666666667,"scrums_won":7,"scrums_total":7,"scrums_success_rate":1.0,"entries_22m":null,"points":29,"tries":null,"points_per_entry":null,"tries_per_entry":null,"game_id":"2024-10-26_2nd_Eastbourne","season":"2024\/25","opposition":"Eastbourne"},{"squad":"2nd","date":"2024-10-26","team":"Opposition","lineouts_won":9,"lineouts_total":13,"lineouts_success_rate":0.6923076923,"scrums_won":7,"scrums_total":7,"scrums_success_rate":1.0,"entries_22m":null,"points":22,"tries":null,"points_per_entry":null,"tries_per_entry":null,"game_id":"2024-10-26_2nd_Eastbourne","season":"2024\/25","opposition":"Eastbourne"},{"squad":"2nd","date":"2024-11-16","team":"EGRFC","lineouts_won":5,"lineouts_total":11,"lineouts_success_rate":0.4545454545,"scrums_won":6,"scrums_total":7,"scrums_success_rate":0.8571428571,"entries_22m":null,"points":26,"tries":null,"points_per_entry":null,"tries_per_entry":null,"game_id":"2024-11-16_2nd_Eastbourne","season":"2024\/25","opposition":"Eastbourne"},{"squad":"2nd","date":"2024-11-16","team":"Opposition","lineouts_won":10,"lineouts_total":12,"lineouts_success_rate":0.8333333333,"scrums_won":11,"scrums_total":11,"scrums_success_rate":1.0,"entries_22m":null,"points":19,"tries":null,"points_per_entry":null,"tries_per_entry":null,"game_id":"2024-11-16_2nd_Eastbourne","season":"2024\/25","opposition":"Eastbourne"},{"squad":"2nd","date":"2024-11-23","team":"EGRFC","lineouts_won":2,"lineouts_total":6,"lineouts_success_rate":0.3333333333,"scrums_won":5,"scrums_total":6,"scrums_success_rate":0.8333333333,"entries_22m":null,"points":7,"tries":null,"points_per_entry":null,"tries_per_entry":null,"game_id":"2024-11-23_2nd_Old_Rutlishians","season":"2024\/25","opposition":"Old Rutlishians"},{"squad":"2nd","date":"2024-11-23","team":"Opposition","lineouts_won":7,"lineouts_total":7,"lineouts_success_rate":1.0,"scrums_won":6,"scrums_total":6,"scrums_success_rate":1.0,"entries_22m":null,"points":24,"tries":null,"points_per_entry":null,"tries_per_entry":null,"game_id":"2024-11-23_2nd_Old_Rutlishians","season":"2024\/25","opposition":"Old Rutlishians"},{"squad":"2nd","date":"2024-11-30","team":"EGRFC","lineouts_won":15,"lineouts_total":19,"lineouts_success_rate":0.7894736842,"scrums_won":5,"scrums_total":6,"scrums_success_rate":0.8333333333,"entries_22m":null,"points":27,"tries":null,"points_per_entry":null,"tries_per_entry":null,"game_id":"2024-11-30_2nd_Newick","season":"2024\/25","opposition":"Newick"},{"squad":"2nd","date":"2024-11-30","team":"Opposition","lineouts_won":6,"lineouts_total":9,"lineouts_success_rate":0.6666666667,"scrums_won":5,"scrums_total":6,"scrums_success_rate":0.8333333333,"entries_22m":null,"points":10,"tries":null,"points_per_entry":null,"tries_per_entry":null,"game_id":"2024-11-30_2nd_Newick","season":"2024\/25","opposition":"Newick"},{"squad":"2nd","date":"2024-12-14","team":"EGRFC","lineouts_won":8,"lineouts_total":14,"lineouts_success_rate":0.5714285714,"scrums_won":6,"scrums_total":8,"scrums_success_rate":0.75,"entries_22m":null,"points":0,"tries":null,"points_per_entry":null,"tries_per_entry":null,"game_id":"2024-12-14_2nd_Barns_Green","season":"2024\/25","opposition":"Barns Green"},{"squad":"2nd","date":"2024-12-14","team":"Opposition","lineouts_won":5,"lineouts_total":12,"lineouts_success_rate":0.4166666667,"scrums_won":10,"scrums_total":10,"scrums_success_rate":1.0,"entries_22m":null,"points":26,"tries":null,"points_per_entry":null,"tries_per_entry":null,"game_id":"2024-12-14_2nd_Barns_Green","season":"2024\/25","opposition":"Barns Green"},{"squad":"2nd","date":"2025-01-18","team":"EGRFC","lineouts_won":13,"lineouts_total":19,"lineouts_success_rate":0.6842105263,"scrums_won":7,"scrums_total":8,"scrums_success_rate":0.875,"entries_22m":null,"points":15,"tries":null,"points_per_entry":null,"tries_per_entry":null,"game_id":"2025-01-18_2nd_Burgess_Hill","season":"2024\/25","opposition":"Burgess Hill"},{"squad":"2nd","date":"2025-01-18","team":"Opposition","lineouts_won":5,"lineouts_total":6,"lineouts_success_rate":0.8333333333,"scrums_won":7,"scrums_total":10,"scrums_success_rate":0.7,"entries_22m":null,"points":8,"tries":null,"points_per_entry":null,"tries_per_entry":null,"game_id":"2025-01-18_2nd_Burgess_Hill","season":"2024\/25","opposition":"Burgess Hill"},{"squad":"2nd","date":"2025-02-08","team":"EGRFC","lineouts_won":5,"lineouts_total":7,"lineouts_success_rate":0.7142857143,"scrums_won":1,"scrums_total":4,"scrums_success_rate":0.25,"entries_22m":null,"points":27,"tries":null,"points_per_entry":null,"tries_per_entry":null,"game_id":"2025-02-08_2nd_Royals","season":"2024\/25","opposition":"Royals"},{"squad":"2nd","date":"2025-02-08","team":"Opposition","lineouts_won":14,"lineouts_total":16,"lineouts_success_rate":0.875,"scrums_won":11,"scrums_total":11,"scrums_success_rate":1.0,"entries_22m":null,"points":17,"tries":null,"points_per_entry":null,"tries_per_entry":null,"game_id":"2025-02-08_2nd_Royals","season":"2024\/25","opposition":"Royals"},{"squad":"2nd","date":"2025-02-15","team":"EGRFC","lineouts_won":3,"lineouts_total":4,"lineouts_success_rate":0.75,"scrums_won":8,"scrums_total":8,"scrums_success_rate":1.0,"entries_22m":null,"points":43,"tries":null,"points_per_entry":null,"tries_per_entry":null,"game_id":"2025-02-15_2nd_Old_Caterhamians","season":"2024\/25","opposition":"Old Caterhamians"},{"squad":"2nd","date":"2025-02-15","team":"Opposition","lineouts_won":9,"lineouts_total":11,"lineouts_success_rate":0.8181818182,"scrums_won":7,"scrums_total":10,"scrums_success_rate":0.7,"entries_22m":null,"points":7,"tries":null,"points_per_entry":null,"tries_per_entry":null,"game_id":"2025-02-15_2nd_Old_Caterhamians","season":"2024\/25","opposition":"Old Caterhamians"},{"squad":"2nd","date":"2025-02-22","team":"EGRFC","lineouts_won":4,"lineouts_total":6,"lineouts_success_rate":0.6666666667,"scrums_won":3,"scrums_total":3,"scrums_success_rate":1.0,"entries_22m":null,"points":34,"tries":null,"points_per_entry":null,"tries_per_entry":null,"game_id":"2025-02-22_2nd_Burgess_Hill","season":"2024\/25","opposition":"Burgess Hill"},{"squad":"2nd","date":"2025-02-22","team":"Opposition","lineouts_won":3,"lineouts_total":3,"lineouts_success_rate":1.0,"scrums_won":4,"scrums_total":4,"scrums_success_rate":1.0,"entries_22m":null,"points":5,"tries":null,"points_per_entry":null,"tries_per_entry":null,"game_id":"2025-02-22_2nd_Burgess_Hill","season":"2024\/25","opposition":"Burgess Hill"},{"squad":"2nd","date":"2025-03-22","team":"EGRFC","lineouts_won":9,"lineouts_total":10,"lineouts_success_rate":0.9,"scrums_won":7,"scrums_total":7,"scrums_success_rate":1.0,"entries_22m":null,"points":58,"tries":null,"points_per_entry":null,"tries_per_entry":null,"game_id":"2025-03-22_2nd_Horsham","season":"2024\/25","opposition":"Horsham"},{"squad":"2nd","date":"2025-03-22","team":"Opposition","lineouts_won":7,"lineouts_total":10,"lineouts_success_rate":0.7,"scrums_won":7,"scrums_total":8,"scrums_success_rate":0.875,"entries_22m":null,"points":14,"tries":null,"points_per_entry":null,"tries_per_entry":null,"game_id":"2025-03-22_2nd_Horsham","season":"2024\/25","opposition":"Horsham"},{"squad":"2nd","date":"2026-01-10","team":"EGRFC","lineouts_won":5,"lineouts_total":8,"lineouts_success_rate":0.625,"scrums_won":10,"scrums_total":10,"scrums_success_rate":1.0,"entries_22m":null,"points":28,"tries":null,"points_per_entry":null,"tries_per_entry":null,"game_id":"2026-01-10_2nd_Uckfield","season":"2025\/26","opposition":"Uckfield"},{"squad":"2nd","date":"2026-01-10","team":"Opposition","lineouts_won":8,"lineouts_total":9,"lineouts_success_rate":0.8888888889,"scrums_won":6,"scrums_total":7,"scrums_success_rate":0.8571428571,"entries_22m":null,"points":21,"tries":null,"points_per_entry":null,"tries_per_entry":null,"game_id":"2026-01-10_2nd_Uckfield","season":"2025\/26","opposition":"Uckfield"},{"squad":"2nd","date":"2026-01-17","team":"EGRFC","lineouts_won":11,"lineouts_total":14,"lineouts_success_rate":0.7857142857,"scrums_won":7,"scrums_total":9,"scrums_success_rate":0.7777777778,"entries_22m":null,"points":5,"tries":null,"points_per_entry":null,"tries_per_entry":null,"game_id":"2026-01-17_2nd_Burgess_Hill","season":"2025\/26","opposition":"Burgess Hill"},{"squad":"2nd","date":"2026-01-17","team":"Opposition","lineouts_won":4,"lineouts_total":9,"lineouts_success_rate":0.4444444444,"scrums_won":7,"scrums_total":8,"scrums_success_rate":0.875,"entries_22m":null,"points":13,"tries":null,"points_per_entry":null,"tries_per_entry":null,"game_id":"2026-01-17_2nd_Burgess_Hill","season":"2025\/26","opposition":"Burgess Hill"},{"squad":"2nd","date":"2026-02-14","team":"EGRFC","lineouts_won":7,"lineouts_total":10,"lineouts_success_rate":0.7,"scrums_won":6,"scrums_total":7,"scrums_success_rate":0.8571428571,"entries_22m":null,"points":7,"tries":null,"points_per_entry":null,"tries_per_entry":null,"game_id":"2026-02-14_2nd_Hove","season":"2025\/26","opposition":"Hove"},{"squad":"2nd","date":"2026-02-14","team":"Opposition","lineouts_won":6,"lineouts_total":6,"lineouts_success_rate":1.0,"scrums_won":9,"scrums_total":9,"scrums_success_rate":1.0,"entries_22m":null,"points":47,"tries":null,"points_per_entry":null,"tries_per_entry":null,"game_id":"2026-02-14_2nd_Hove","season":"2025\/26","opposition":"Hove"},{"squad":"2nd","date":"2026-03-07","team":"EGRFC","lineouts_won":6,"lineouts_total":6,"lineouts_success_rate":1.0,"scrums_won":4,"scrums_total":5,"scrums_success_rate":0.8,"entries_22m":null,"points":31,"tries":null,"points_per_entry":null,"tries_per_entry":null,"game_id":"2026-03-07_2nd_Hellingly","season":"2025\/26","opposition":"Hellingly"},{"squad":"2nd","date":"2026-03-07","team":"Opposition","lineouts_won":7,"lineouts_total":10,"lineouts_success_rate":0.7,"scrums_won":9,"scrums_total":11,"scrums_success_rate":0.8181818182,"entries_22m":null,"points":5,"tries":null,"points_per_entry":null,"tries_per_entry":null,"game_id":"2026-03-07_2nd_Hellingly","season":"2025\/26","opposition":"Hellingly"},{"squad":"2nd","date":"2026-03-28","team":"EGRFC","lineouts_won":3,"lineouts_total":6,"lineouts_success_rate":0.5,"scrums_won":8,"scrums_total":8,"scrums_success_rate":1.0,"entries_22m":null,"points":22,"tries":null,"points_per_entry":null,"tries_per_entry":null,"game_id":"2026-03-28_2nd_Crowborough","season":"2025\/26","opposition":"Crowborough"},{"squad":"2nd","date":"2026-03-28","team":"Opposition","lineouts_won":13,"lineouts_total":14,"lineouts_success_rate":0.9285714286,"scrums_won":7,"scrums_total":10,"scrums_success_rate":0.7,"entries_22m":null,"points":12,"tries":null,"points_per_entry":null,"tries_per_entry":null,"game_id":"2026-03-28_2nd_Crowborough","season":"2025\/26","opposition":"Crowborough"},{"squad":"2nd","date":"2026-04-11","team":"EGRFC","lineouts_won":3,"lineouts_total":6,"lineouts_success_rate":0.5,"scrums_won":13,"scrums_total":14,"scrums_success_rate":0.9285714286,"entries_22m":null,"points":29,"tries":null,"points_per_entry":null,"tries_per_entry":null,"game_id":"2026-04-11_2nd_Uckfield","season":"2025\/26","opposition":"Uckfield"},{"squad":"2nd","date":"2026-04-11","team":"Opposition","lineouts_won":4,"lineouts_total":9,"lineouts_success_rate":0.4444444444,"scrums_won":9,"scrums_total":10,"scrums_success_rate":0.9,"entries_22m":null,"points":17,"tries":null,"points_per_entry":null,"tries_per_entry":null,"game_id":"2026-04-11_2nd_Uckfield","season":"2025\/26","opposition":"Uckfield"}]