{
    "2016/17": {
        "1st": {
            "PlayersUsed": 19,
            "Players_A": "S Anderson / Dan Arnold / Bertram Beanland / Dave Bridges / Morgan Burger / J Carr / S Cooke / Ryan Foster / James Funnell / Daan Hulst / Connor Leggat / Sam Montagu / Mark Oliver / John Peaty / R Perry / F Robinson / T Sandys / B Swadling / M Taylor  (1.0)",
            "Players_T": "S Anderson / Dan Arnold / J Carr / James Funnell / F Robinson  (1)"
        },
        "2nd": {
            "PlayersUsed": 47,
            "Players_A": "Matt Marriott  (6.0)",
            "Players_T": "Robert Poole  (3)"
        },
        "Total": {
            "PlayersUsed": 58,
            "Players_A": "Matt Marriott  (6.0)",
            "Players_T": "Robert Poole  (3)"
        }
    },
    "2017/18": {
        "1st": {
            "PlayersUsed": 47,
            "Players_A": "Mark Oliver  (18.0)",
            "Players_T": "Sam Montagu  (12)"
        },
        "2nd": {
            "PlayersUsed": 65,
            "Players_A": "Tom Halligey  (12.0)",
            "Players_T": "Jake Radcliffe  (7)"
        },
        "Total": {
            "PlayersUsed": 87,
            "Players_A": "Mark Oliver  (18.0)",
            "Players_T": "Sam Montagu  (12)"
        }
    },
    "2018/19": {
        "1st": {
            "PlayersUsed": 55,
            "Players_A": "Fin Edwards  (17.0)",
            "Players_T": "Ben Beard  (13)"
        },
        "2nd": {
            "PlayersUsed": 75,
            "Players_A": "Oli Brown   (16.0)",
            "Players_T": "Tom Halligey  (6)"
        },
        "Total": {
            "PlayersUsed": 90,
            "Players_A": "Fin Edwards  (17.0)",
            "Players_T": "Ben Beard  (13)"
        }
    },
    "2019/20": {
        "1st": {
            "PlayersUsed": 48,
            "Players_A": "Ollie Adams / Jack Andrews  (15.0)",
            "Players_T": "Ben Beard  (12)"
        },
        "2nd": {
            "PlayersUsed": 48,
            "Players_A": "Darren Gwynn / Matt Marriott  (7.0)",
            "Players_T": "Jack Skipworth  (3)"
        },
        "Total": {
            "PlayersUsed": 75,
            "Players_A": "Ollie Adams / Jack Andrews  (15.0)",
            "Players_T": "Ben Beard  (12)"
        }
    },
    "2021/22": {
        "1st": {
            "PlayersUsed": 60,
            "Players_A": "Max Crawley-Moore / Ryan Morlen  (19.0)",
            "Players_T": "Fergus Wood  (22)"
        },
        "2nd": {
            "PlayersUsed": 84,
            "Players_A": "Harrison Berry  (18.0)",
            "Players_T": "Ethan Carrick  (9)"
        },
        "Total": {
            "PlayersUsed": 101,
            "Players_A": "Max Crawley-Moore / Ryan Morlen  (19.0)",
            "Players_T": "Fergus Wood  (22)"
        }
    },
    "2022/23": {
        "1st": {
            "PlayersUsed": 41,
            "Players_A": "Max Crawley-Moore / Ben Tottman / John Peaty  (18.0)",
            "Players_T": "Ryan Morlen  (20)"
        },
        "2nd": {
            "PlayersUsed": 73,
            "Players_A": "Harrison Berry  (12.0)",
            "Players_T": "Will Roberts  (7)"
        },
        "Total": {
            "PlayersUsed": 90,
            "Players_A": "Max Crawley-Moore / Ben Tottman / John Peaty  (18.0)",
            "Players_T": "Ryan Morlen  (20)"
        }
    },
    "2023/24": {
        "1st": {
            "PlayersUsed": 55,
            "Players_A": "Guy Collins / Ryland Thomas / Ben Tottman  (25.0)",
            "Players_T": "Jake Radcliffe  (11)"
        },
        "2nd": {
            "PlayersUsed": 81,
            "Players_A": "Harrison Berry  (14.0)",
            "Players_T": "Will Roberts  (15)"
        },
        "Total": {
            "PlayersUsed": 96,
            "Players_A": "Guy Collins / Ryland Thomas / Ben Tottman  (25.0)",
            "Players_T": "Will Roberts  (15)"
        }
    },
    "2024/25": {
        "1st": {
            "PlayersUsed": 50,
            "Players_A": "Sam Lindsay-McCall  (18.0)",
            "Players_T": "Jake Radcliffe  (6)"
        },
        "2nd": {
            "PlayersUsed": 86,
            "Players_A": "Harrison Berry  (15.0)",
            "Players_T": "Jack Billin  (6)"
        },
        "Total": {
            "PlayersUsed": 96,
            "Players_A": "Sam Lindsay-McCall  (18.0)",
            "Players_T": "Jake Radcliffe / Jack Billin  (6)"
        }
    }
}