{"config": {"axis": {"labelFont": "Lato, sans-serif", "titleFont": "PT Sans Narrow, Helvetica Neue, Helvetica, Arial, sans-serif", "labelFontSize": 13, "titleFontSize": 24, "gridColor": "#202947", "gridOpacity": 0.2}, "header": {"labelFont": "PT Sans Narrow, Helvetica Neue, Helvetica, Arial, sans-serif", "titleFont": "PT Sans Narrow, Helvetica Neue, Helvetica, Arial, sans-serif", "labelFontSize": 24, "titleFontSize": 28, "labelFontWeight": "bold", "orient": "left"}, "legend": {"labelFont": "Lato, sans-serif", "titleFont": "PT Sans Narrow, Helvetica Neue, Helvetica, Arial, sans-serif", "labelFontSize": 14, "titleFontSize": 16, "titlePadding": 5, "fillColor": "white", "strokeColor": "black", "padding": 10, "titleFontWeight": "lighter", "titleFontStyle": "italic", "titleColor": "gray", "offset": 10}, "title": {"font": "PT Sans Narrow, Helvetica Neue, Helvetica, Arial, sans-serif", "fontSize": 48, "fontWeight": "bold", "anchor": "start", "align": "center", "titlePadding": 20, "subtitlePadding": 10, "subtitleFontSize": 13, "subtitleColor": "", "subtitleFontStyle": "italic", "offset": 15, "color": "black"}, "axisX": {"labelAngle": 0}, "facet": {"title": null, "header": null, "align": {"row": "each", "column": "each"}}, "resolve": {"scale": {"y": "independent", "facet": "independent"}}, "background": "#f2f1f4"}, "vconcat": [{"data": {"name": "data-51878ae92c9ecf21c900aeb6a79e3e7c"}, "mark": {"type": "bar"}, "encoding": {"color": {"field": "numbers", "legend": {"title": "Numbers"}, "scale": {"domain": ["4", "5", "6", "7"], "range": ["#ca0020", "#f4a582", "#92c5de", "#0571b0"]}, "sort": ["4", "5", "6", "7"], "type": "nominal"}, "tooltip": [{"field": "season", "title": "Season", "type": "nominal"}, {"field": "numbers", "title": "Numbers", "type": "nominal"}, {"field": "won", "title": "Won", "type": "quantitative"}, {"field": "total", "title": "Total", "type": "quantitative"}, {"field": "success_rate", "format": ".0%", "title": "Success Rate", "type": "quantitative"}], "x": {"axis": {"labelAngle": -30}, "field": "season", "sort": ["2021/22", "2022/23", "2023/24", "2024/25", "2025/26"], "title": null, "type": "nominal"}, "xOffset": {"field": "numbers", "sort": ["4", "5", "6", "7"], "type": "nominal"}, "y": {"axis": {"format": "%"}, "field": "success_rate", "scale": {"domain": [0, 1]}, "title": "Success Rate", "type": "quantitative"}}, "height": 220, "title": {"text": "By Numbers", "subtitle": "4/5/6/7 man lineout"}, "width": {"step": 14}}, {"data": {"name": "data-72365f07a58529c13b170f7854a513fb"}, "mark": {"type": "bar"}, "encoding": {"color": {"field": "area", "legend": {"title": "Area"}, "scale": {"domain": ["Front", "Middle", "Back"], "range": ["#981515", "#e8983e", "#146f14"]}, "sort": ["Front", "Middle", "Back"], "type": "nominal"}, "tooltip": [{"field": "season", "title": "Season", "type": "nominal"}, {"field": "area", "title": "Area", "type": "nominal"}, {"field": "won", "title": "Won", "type": "quantitative"}, {"field": "total", "title": "Total", "type": "quantitative"}, {"field": "success_rate", "format": ".0%", "title": "Success Rate", "type": "quantitative"}], "x": {"axis": {"labelAngle": -30}, "field": "season", "sort": ["2021/22", "2022/23", "2023/24", "2024/25", "2025/26"], "title": "Season", "type": "nominal"}, "xOffset": {"field": "area", "sort": ["Front", "Middle", "Back"], "type": "nominal"}, "y": {"axis": {"format": "%"}, "field": "success_rate", "scale": {"domain": [0, 1]}, "title": "Success Rate", "type": "quantitative"}}, "height": 220, "title": {"text": "By Area", "subtitle": "Front/Middle/Back"}, "width": {"step": 14}}], "spacing": 24, "title": {"text": "1st XV Lineout Breakdown", "subtitle": "Success rate by numbers and throw area."}, "$schema": "https://vega.github.io/schema/vega-lite/v5.20.1.json", "datasets": {"data-51878ae92c9ecf21c900aeb6a79e3e7c": [{"season": "2021/22", "numbers": "4", "total": 45, "won": 40, "success_rate": 0.8888888888888888}, {"season": "2021/22", "numbers": "5", "total": 24, "won": 19, "success_rate": 0.7916666666666666}, {"season": "2021/22", "numbers": "6", "total": 35, "won": 32, "success_rate": 0.9142857142857143}, {"season": "2021/22", "numbers": "7", "total": 5, "won": 5, "success_rate": 1.0}, {"season": "2022/23", "numbers": "4", "total": 74, "won": 64, "success_rate": 0.8648648648648649}, {"season": "2022/23", "numbers": "5", "total": 58, "won": 50, "success_rate": 0.8620689655172413}, {"season": "2022/23", "numbers": "6", "total": 42, "won": 34, "success_rate": 0.8095238095238095}, {"season": "2022/23", "numbers": "7", "total": 3, "won": 2, "success_rate": 0.6666666666666666}, {"season": "2023/24", "numbers": "4", "total": 100, "won": 71, "success_rate": 0.71}, {"season": "2023/24", "numbers": "5", "total": 43, "won": 25, "success_rate": 0.5813953488372093}, {"season": "2023/24", "numbers": "6", "total": 60, "won": 44, "success_rate": 0.7333333333333333}, {"season": "2023/24", "numbers": "7", "total": 88, "won": 63, "success_rate": 0.7159090909090909}, {"season": "2024/25", "numbers": "4", "total": 6, "won": 4, "success_rate": 0.6666666666666666}, {"season": "2024/25", "numbers": "5", "total": 2, "won": 2, "success_rate": 1.0}, {"season": "2024/25", "numbers": "6", "total": 7, "won": 2, "success_rate": 0.2857142857142857}, {"season": "2024/25", "numbers": "7", "total": 202, "won": 149, "success_rate": 0.7376237623762376}, {"season": "2025/26", "numbers": "4", "total": 39, "won": 31, "success_rate": 0.7948717948717948}, {"season": "2025/26", "numbers": "5", "total": 103, "won": 87, "success_rate": 0.8446601941747572}, {"season": "2025/26", "numbers": "7", "total": 2, "won": 2, "success_rate": 1.0}], "data-72365f07a58529c13b170f7854a513fb": [{"season": "2021/22", "area": "Back", "total": 21, "won": 20, "success_rate": 0.9523809523809523}, {"season": "2021/22", "area": "Front", "total": 30, "won": 26, "success_rate": 0.8666666666666667}, {"season": "2021/22", "area": "Middle", "total": 58, "won": 50, "success_rate": 0.8620689655172413}, {"season": "2022/23", "area": "Back", "total": 26, "won": 21, "success_rate": 0.8076923076923077}, {"season": "2022/23", "area": "Front", "total": 60, "won": 54, "success_rate": 0.9}, {"season": "2022/23", "area": "Middle", "total": 91, "won": 75, "success_rate": 0.8241758241758241}, {"season": "2023/24", "area": "Back", "total": 63, "won": 40, "success_rate": 0.6349206349206349}, {"season": "2023/24", "area": "Front", "total": 97, "won": 74, "success_rate": 0.7628865979381443}, {"season": "2023/24", "area": "Middle", "total": 131, "won": 89, "success_rate": 0.6793893129770993}, {"season": "2024/25", "area": "Back", "total": 46, "won": 31, "success_rate": 0.6739130434782609}, {"season": "2024/25", "area": "Front", "total": 45, "won": 38, "success_rate": 0.8444444444444444}, {"season": "2024/25", "area": "Middle", "total": 126, "won": 88, "success_rate": 0.6984126984126984}, {"season": "2025/26", "area": "Back", "total": 22, "won": 15, "success_rate": 0.6818181818181818}, {"season": "2025/26", "area": "Front", "total": 49, "won": 42, "success_rate": 0.8571428571428571}, {"season": "2025/26", "area": "Middle", "total": 73, "won": 63, "success_rate": 0.863013698630137}]}}